Workbook

Sheet Vendors
A1: vendor_id | B1: vendor_name | C1: category | D1: region | E1: active | H1: PK uniqueness
A2: VEND1000 | B2: Johnson-Howard | C2: Supplies | D2: East | E2: Y | H2: =COUNTIF(A:A,A2) -> 1
A3: VEND1001 | B3: Jensen Ltd | C3: Consulting | D3: South | E3: Y | H3: =COUNTIF(A:A,A3) -> 1
A4: VEND1002 | B4: Collins Group | C4: Services | D4: North | E4: Y | H4: =COUNTIF(A:A,A4) -> 1
A5: VEND1003 | B5: Smith, Kirby and Torres | C5: Utilities | D5: North | E5: Y | H5: =COUNTIF(A:A,A5) -> 1
A6: VEND1004 | B6: Mcgrath, Wheeler and Boyd | C6: Utilities | D6: North | E6: Y | H6: =COUNTIF(A:A,A6) -> 1
A7: VEND1005 | B7: Cooper-Larson | C7: Supplies | D7: South | E7: Y | H7: =COUNTIF(A:A,A7) -> 1
A8: VEND1006 | B8: Ward-David | C8: Utilities | D8: South | E8: Y | H8: =COUNTIF(A:A,A8) -> 1
A9: VEND1007 | B9: Savage Ltd | C9: Utilities | D9: West | E9: Y | H9: =COUNTIF(A:A,A9) -> 1
A10: VEND1008 | B10: Medina-Lee | C10: Services | D10: South | E10: Y | H10: =COUNTIF(A:A,A10) -> 1
A11: VEND1009 | B11: Griffith and Sons | C11: Services | D11: East | E11: Y | H11: =COUNTIF(A:A,A11) -> 1
A12: VEND1010 | B12: Thomas-Santana | C12: Rent | D12: South | E12: Y | H12: =COUNTIF(A:A,A12) -> 1
A13: VEND1011 | B13: Robinson-Gibbs | C13: Services | D13: West | E13: Y | H13: =COUNTIF(A:A,A13) -> 1
... A121: VEND1119 | B121: Graham-Lopez | C121: Consulting | D121: North | E121: N | H121: =COUNTIF(A:A,A121) -> 1

Sheet Headcount
A1: employee_id | B1: employee_name | C1: business_unit | D1: join_date | E1: status | F1: region | G1: cost_to_company | J1: PK uniqueness
A2: EMP1000 | B2: Daniel Thornton | C2: Enterprise | D2: 44968 | E2: Active | F2: South | G2: 1566441 | J2: =COUNTIF(A:A,A2) -> 1
A3: EMP1001 | B3: Ashley Burch | C3: Retail | D3: 44084 | E3: Active | F3: West | G3: 1533942 | J3: =COUNTIF(A:A,A3) -> 1
A4: EMP1002 | B4: Angel Perry | C4: Online | D4: 44620 | E4: Active | F4: East | G4: 962333 | J4: =COUNTIF(A:A,A4) -> 1
A5: EMP1003 | B5: Kimberly Harmon | C5: Online | D5: 44484 | E5: Active | F5: North | G5: 503403 | J5: =COUNTIF(A:A,A5) -> 1
A6: EMP1004 | B6: Sarah Smith DDS | C6: Enterprise | D6: 44957 | E6: Active | F6: West | G6: 1051271 | J6: =COUNTIF(A:A,A6) -> 1
A7: EMP1005 | B7: Sierra Jordan | C7: Enterprise | D7: 44945 | E7: Active | F7: South | G7: 731473 | J7: =COUNTIF(A:A,A7) -> 1
A8: EMP1006 | B8: Adam Wood | C8: Enterprise | D8: 43768 | E8: Active | F8: West | G8: 596883 | J8: =COUNTIF(A:A,A8) -> 1
A9: EMP1007 | B9: Keith Collins | C9: Online | D9: 44993 | E9: Active | F9: East | G9: 864597 | J9: =COUNTIF(A:A,A9) -> 1
A10: EMP1008 | B10: Mitchell Kelly | C10: Enterprise | D10: 44438 | E10: Active | F10: North | G10: 1736454 | J10: =COUNTIF(A:A,A10) -> 1
A11: EMP1009 | B11: Jacob Mendez | C11: Enterprise | D11: 45166 | E11: Active | F11: North | G11: 1479884 | J11: =COUNTIF(A:A,A11) -> 1
A12: EMP1010 | B12: William Bryant | C12: Enterprise | D12: 44563 | E12: Active | F12: North | G12: 1160373 | J12: =COUNTIF(A:A,A12) -> 1
A13: EMP1011 | B13: Sean Daniels | C13: Retail | D13: 44741 | E13: Active | F13: South | G13: 1603487 | J13: =COUNTIF(A:A,A13) -> 1
... A201: EMP1199 | B201: Mr. Alec Nelson | C201: Enterprise | D201: 44808 | E201: Inactive | F201: South | G201: 728593 | J201: =COUNTIF(A:A,A201) -> 1

Sheet analysis
A3: Row Labels | B3: Sum of amount | C3: Count of category | E3: Row Labels | F3: Sum of amount | G3: Sum of amount2 | I3: Row Labels | J3: Sum of amount | K3: Sum of amount2 | M3: Row Labels | N3: Sum of amount | P3: Row Labels | Q3: Sum of amount | S3: Row Labels | T3: Sum of amount | V3: Row Labels | W3: Sum of amount
A4: Asset | B4: 6270940.2 | C4: 315 | E4: Asset | F4: 6270940.2 | G4: 0.0088081259 | I4: Asset | J4: 6270940.2 | K4: 0.0088081259 | M4: Acosta LLC | N4: 3262151.5 | P4: East | Q4: 2.0318647e+08 | S4: Alexander-Arnold | T4: -2450171.9 | V4: Consulting | W4: -13555425
A5: Equity | B5: 4882558.6 | C5: 244 | E5: Equity | F5: 4882558.6 | G5: 0.0068580131 | I5: Enterprise | J5: 1976152.8 | K5: 0.0027756927 | M5: Adams LLC | N5: 1909789.2 | P5: North | Q5: 1.8587358e+08 | S5: Atkinson Ltd | T5: -570810.32 | V5: Rent | W5: -48186512
A6: Liability | B6: 3928643 | C6: 202 | E6: Expense | F6: -1.677413e+08 | G6: -0.23560845 | I6: Online | J6: 2260972.4 | K6: 0.0031757486 | M6: Aguilar-Mitchell | N6: 2250006.6 | P6: South | Q6: 2.0821065e+08 | S6: Austin, Thompson and Larson | T6: -610181.11 | V6: Services | W6: -18328181
A7: Marketing | B7: -28960158 | C7: 698 | E7: Liability | F7: 3928643 | G7: 0.005518149 | I7: Retail | J7: 2033815 | K7: 0.0028566846 | M7: Allen and Sons | N7: 1802589.7 | P7: West | Q7: 2.6733789e+08 | S7: Austin-Steele | T7: -2353395.7 | V7: Supplies | W7: -41767494
A8: Other | B8: -29959342 | C8: 724 | E8: Revenue | F8: 8.6460859e+08 | G8: 1.2144242 | I8: Equity | J8: 4882558.6 | K8: 0.0068580131 | M8: Allen, Walker and Jones | N8: 2240439.9 | P8: Grand Total | Q8: 8.6460859e+08 | S8: Baker, Krueger and Delacruz | T8: -790935.55 | V8: Utilities | W8: -45903687
A9: Payroll | B9: -25306519 | C9: 652 | E9: Grand Total | F9: 7.1194943e+08 | G9: 1 | I9: Enterprise | J9: 1624567.9 | K9: 0.0022818585 | M9: Allison, Rhodes and Gardner | N9: 2383188.1 | S9: Banks-Davis | T9: -1425449.5 | V9: Grand Total | W9: -1.677413e+08
A10: Product | B10: 2.8412251e+08 | C10: 1797 | I10: Online | J10: 1830613.8 | K10: 0.0025712694 | M10: Alvarez, Chang and Brown | N10: 1900542.7 | S10: Berry, Ruiz and Moses | T10: -2006372.4
A11: Rent | B11: -27384083 | C11: 659 | I11: Retail | J11: 1427376.9 | K11: 0.0020048852 | M11: Anderson LLC | N11: 4221501 | S11: Blackburn-Thomas | T11: -1856673.6
A12: Service | B12: 2.8863457e+08 | C12: 1851 | I12: Expense | J12: -1.677413e+08 | K12: -0.23560845 | M12: Anderson, Weeks and Gonzalez | N12: 1743642.1 | S12: Bowers-Fisher | T12: -1607724.1
A13: Subscription | B13: 2.9185151e+08 | C13: 1866 | I13: Enterprise | J13: -57022619 | K13: -0.080093636 | M13: Anderson-Ellis | N13: 2641934.2 | S13: Boyd, Lozano and Gomez | T13: -2677039
A14: Supplies | B14: -27747509 | C14: 688 | E14: Row Labels | F14: Sum of budgeted_expense | G14: Sum of budgeted_revenue | I14: Online | J14: -55303538 | K14: -0.077679025 | M14: Archer PLC | N14: 1965728.9 | S14: Brown Group | T14: -700066.14
A15: Utilities | B15: -28383689 | C15: 704 | E15: Enterprise | F15: 33589523 | G15: 44676492 | I15: Retail | J15: -55415143 | K15: -0.077835786 | M15: Atkinson, Garcia and Bass | N15: 2199264.8 | S15: Brown Inc | T15: -734207.87
A16: Grand Total | B16: 7.1194943e+08 | C16: 10400 | E16: Online | F16: 37134010 | G16: 47304384 | I16: Liability | J16: 3928643 | K16: 0.005518149 | M16: Austin PLC | N16: 3093202.8 | S16: Brown, Powers and Weeks | T16: -2303228.3 | V16: Row Labels | W16: Sum of amount
E17: Retail | F17: 33541736 | G17: 43833108 | I17: Enterprise | J17: 1204104.5 | K17: 0.0016912781 | M17: Austin, Hooper and Miller | N17: 2951578.4 | P17: Row Labels | Q17: Sum of amount | S17: Bryan, Mcintyre and Frye | T17: -1905521.6 | V17: East | W17: -41146133
E18: Grand Total | F18: 104265269 | G18: 135813984 | I18: Online | J18: 1361137.7 | K18: 0.0019118461 | M18: Avila-Harris | N18: 3167900.3 | P18: Enterprise | Q18: 2.6383334e+08 | S18: Burke LLC | T18: -761483.94 | V18: North | W18: -42749176
I19: Retail | J19: 1363400.8 | K19: 0.0019150247 | M19: Baker Inc | N19: 922914.41 | P19: Online | Q19: 2.8058341e+08 | S19: Campbell-Anthony | T19: -1674527.9 | V19: South | W19: -42494120
I20: Revenue | J20: 8.6460859e+08 | K20: 1.2144242 | M20: Baker, Cisneros and Cross | N20: 1859969.2 | P20: Retail | Q20: 3.2019184e+08 | S20: Carson, Pena and Phelps | T20: -428554.39 | V20: West | W20: -41351870
I21: Enterprise | J21: 2.813972e+08 | K21: 0.39524886 | M21: Ball Group | N21: 1568737.8 | P21: Grand Total | Q21: 8.6460859e+08 | S21: Castro-Bentley | T21: -1802700 | V21: Grand Total | W21: -1.677413e+08
I22: Online | J22: 2.9753292e+08 | K22: 0.417913 | M22: Barnes, Williams and Pennington | N22: 1808623.6 | S22: Chang LLC | T22: -1444869
I23: Retail | J23: 2.8567847e+08 | K23: 0.4012623 | M23: Barnett Group | N23: 2544324 | S23: Collins Group | T23: -630941.59
I24: Grand Total | J24: 7.1194943e+08 | K24: 1 | M24: Bass, Stewart and Long | N24: 2415807.6 | S24: Cooper-Larson | T24: -2142017.3
M25: Bass-Marsh | N25: 2991967.2 | S25: Crawford, Solis and Jackson | T25: -2831133
M26: Beck-Schmitt | N26: 3221717.6 | S26: Cross Group | T26: -1961156.8
M27: Bell LLC | N27: 1493776 | S27: Dennis, Perry and Bean | T27: -1500375.5
M28: Bentley, Ibarra and Anderson | N28: 1868511.1 | S28: Dominguez, King and Kaufman | T28: -2461698
M29: Berry Inc | N29: 2071565.3 | S29: Dorsey, Barrera and Parker | T29: -2731307.6
M30: Berry-Mckee | N30: 2145061.2 | S30: Doyle, Pitts and Logan | T30: -2049119.1
M31: Black Group | N31: 1412823.4 | S31: Duncan, Henry and Hill | T31: -1972614.1
M32: Booker, Gomez and Jones | N32: 2575645.3 | S32: Dunn and Sons | T32: -554792.13
M33: Boyd, James and Parsons | N33: 2218608.4 | S33: Dunn, Mann and Huber | T33: -1321259.7
M34: Brooks Group | N34: 1952138.9 | S34: Ellis, Ortiz and Chen | T34: -745241.25
M35: Brooks, Aguilar and Young | N35: 1752786.1 | S35: Fernandez, Mcintyre and Hamilton | T35: -1594786.6
M36: Brown Group | N36: 3585671.7 | S36: Fields, Carey and Salazar | T36: -499854.23
... M125: Hampton-Livingston | N125: 2215740.2 | S125: Grand Total | T125: 7.1194943e+08
M126: Hancock LLC | N126: 3389917.5
M127: Hardy-Wong | N127: 2959049.4
M128: Harrell-Burnett | N128: 2520397.1
M129: Harris LLC | N129: 3460340.7
M130: Harris Ltd | N130: 2066010
M131: Harrison Group | N131: 2276490
M132: Harrison LLC | N132: 3265342.3
M133: Hayes, Ramos and Munoz | N133: 2387880.1
M134: Henry, Jones and Farley | N134: 1425815.1
M135: Hernandez PLC | N135: 2819595.3
M136: Hernandez, Andrews and Gomez | N136: 1877077.8
M137: Hernandez, Stuart and Mejia | N137: 1924920.7
... M377: Grand Total | N377: 7.1194943e+08

Sheet Financial_Transactions
A1: transaction_id | B1: transaction_date | C1: amount | D1: account_type | E1: category | F1: business_unit | G1: region | H1: customer_id | I1: name | J1: vendor_id | K1: description | L1: T_DATE STATUS | M1: AMOUNT STATUS | N1: PK uniqueness | O1: FTV | P1: FTC | Q1: ACCOUNT TYPE STATUS | R1: BU STATUS
A2: TRX100000 | B2: 45172 | C2: -66631.73 | D2: Expense | E2: Supplies | F2: Online | G2: West | I2: =_xlfn.XLOOKUP(H2,'Customers'!A2:A401,'Customers'!B2:B401," ") | J2: VEND1053 | K2: Begin catch control dark practice. | L2: =IF(ISERROR(B2),"ERORROR","OK") -> OK | M2: =IF(ISNA(C3),"NULL","NOT NULL") -> NOT NULL | N2: =COUNTIF(A:A,A2) -> 1 | O2: =IF(ISNA(VLOOKUP(J2,Vendors!A:A,1,FALSE)),"MISSING VENDER","VALID") -> VALID | P2: =IF(ISNA(VLOOKUP(H2,'Customers'!A:A,1,FALSE)),"missing customer ","valid") -> missing customer | Q2: =IF(ISBLANK(D2),"INVALID","VALID") -> VALID | R2: =IF(ISNA(F2),"INVALID","VALID") -> VALID
A3: TRX100001 | B3: 45182 | C3: -54305.58 | D3: Expense | E3: Utilities | F3: Enterprise | G3: East | I3: =_xlfn.XLOOKUP(H3,'Customers'!A3:A402,'Customers'!B3:B402," ") | J3: VEND1059 | K3: Style guy soldier boy energy above. | L3: =IF(ISERROR(B3),"ERORROR","OK") -> OK | M3: =IF(ISNA(C4),"NULL","NOT NULL") -> NOT NULL | N3: =COUNTIF(A:A,A3) -> 1 | O3: =IF(ISNA(VLOOKUP(J3,Vendors!A:A,1,FALSE)),"MISSING VENDER","VALID") -> VALID | P3: =IF(ISNA(VLOOKUP(H3,'Customers'!A:A,1,FALSE)),"missing customer ","valid") -> missing customer | Q3: =IF(ISBLANK(D3),"INVALID","VALID") -> VALID | R3: =IF(ISNA(F3),"INVALID","VALID") -> VALID
A4: TRX100002 | B4: 45104 | C4: 146074.92 | D4: Revenue | E4: Subscription | F4: Online | G4: East | H4: CUST10122 | I4: =_xlfn.XLOOKUP(H4,'Customers'!A4:A403,'Customers'!B4:B403," ") -> Kelly-Smith | K4: Skill surface drug personal western. | L4: =IF(ISERROR(B4),"ERORROR","OK") -> OK | M4: =IF(ISNA(C5),"NULL","NOT NULL") -> NOT NULL | N4: =COUNTIF(A:A,A4) -> 1 | O4: =IF(ISNA(VLOOKUP(J4,Vendors!A:A,1,FALSE)),"MISSING VENDER","VALID") -> MISSING VENDER | P4: =IF(ISNA(VLOOKUP(H4,'Customers'!A:A,1,FALSE)),"missing customer ","valid") -> valid | Q4: =IF(ISBLANK(D4),"INVALID","VALID") -> VALID | R4: =IF(ISNA(F4),"INVALID","VALID") -> VALID
A5: TRX100003 | B5: 45102 | C5: 212157.95 | D5: Revenue | E5: Service | F5: Enterprise | G5: West | H5: CUST10027 | I5: =_xlfn.XLOOKUP(H5,'Customers'!A5:A404,'Customers'!B5:B404," ") -> Bass-Marsh | K5: Develop many it I rich floor decide. | L5: =IF(ISERROR(B5),"ERORROR","OK") -> OK | M5: =IF(ISNA(C6),"NULL","NOT NULL") -> NOT NULL | N5: =COUNTIF(A:A,A5) -> 1 | O5: =IF(ISNA(VLOOKUP(J5,Vendors!A:A,1,FALSE)),"MISSING VENDER","VALID") -> MISSING VENDER | P5: =IF(ISNA(VLOOKUP(H5,'Customers'!A:A,1,FALSE)),"missing customer ","valid") -> valid | Q5: =IF(ISBLANK(D5),"INVALID","VALID") -> VALID | R5: =IF(ISNA(F5),"INVALID","VALID") -> VALID
A6: TRX100004 | B6: 45245 | C6: -35944.73 | D6: Expense | E6: Rent | F6: Enterprise | G6: North | I6: =_xlfn.XLOOKUP(H6,'Customers'!A6:A405,'Customers'!B6:B405," ") | J6: VEND1046 | K6: Choose thought teach never. | L6: =IF(ISERROR(B6),"ERORROR","OK") -> OK | M6: =IF(ISNA(C7),"NULL","NOT NULL") -> NOT NULL | N6: =COUNTIF(A:A,A6) -> 1 | O6: =IF(ISNA(VLOOKUP(J6,Vendors!A:A,1,FALSE)),"MISSING VENDER","VALID") -> VALID | P6: =IF(ISNA(VLOOKUP(H6,'Customers'!A:A,1,FALSE)),"missing customer ","valid") -> missing customer | Q6: =IF(ISBLANK(D6),"INVALID","VALID") -> VALID | R6: =IF(ISNA(F6),"INVALID","VALID") -> VALID
A7: TRX100005 | B7: 44989 | C7: 90953.83 | D7: Revenue | E7: Service | F7: Retail | G7: South | H7: CUST10332 | I7: =_xlfn.XLOOKUP(H7,'Customers'!A7:A406,'Customers'!B7:B406," ") -> Calhoun-Estrada | K7: Dinner present unit lay course. | L7: =IF(ISERROR(B7),"ERORROR","OK") -> OK | M7: =IF(ISNA(C8),"NULL","NOT NULL") -> NOT NULL | N7: =COUNTIF(A:A,A7) -> 1 | O7: =IF(ISNA(VLOOKUP(J7,Vendors!A:A,1,FALSE)),"MISSING VENDER","VALID") -> MISSING VENDER | P7: =IF(ISNA(VLOOKUP(H7,'Customers'!A:A,1,FALSE)),"missing customer ","valid") -> valid | Q7: =IF(ISBLANK(D7),"INVALID","VALID") -> VALID | R7: =IF(ISNA(F7),"INVALID","VALID") -> VALID
A8: TRX100006 | B8: 45115 | C8: 73251.21 | D8: Revenue | E8: Service | F8: Online | G8: West | H8: CUST10270 | I8: =_xlfn.XLOOKUP(H8,'Customers'!A8:A407,'Customers'!B8:B407," ") -> Miles Ltd | K8: Data ago arm care hundred represent wonder. | L8: =IF(ISERROR(B8),"ERORROR","OK") -> OK | M8: =IF(ISNA(C9),"NULL","NOT NULL") -> NOT NULL | N8: =COUNTIF(A:A,A8) -> 1 | O8: =IF(ISNA(VLOOKUP(J8,Vendors!A:A,1,FALSE)),"MISSING VENDER","VALID") -> MISSING VENDER | P8: =IF(ISNA(VLOOKUP(H8,'Customers'!A:A,1,FALSE)),"missing customer ","valid") -> valid | Q8: =IF(ISBLANK(D8),"INVALID","VALID") -> VALID | R8: =IF(ISNA(F8),"INVALID","VALID") -> VALID
A9: TRX100007 | B9: 44644 | C9: -21064.02 | D9: Expense | E9: Marketing | F9: Online | G9: East | I9: =_xlfn.XLOOKUP(H9,'Customers'!A9:A408,'Customers'!B9:B408," ") | J9: VEND1115 | K9: Sign such remember range ability. | L9: =IF(ISERROR(B9),"ERORROR","OK") -> OK | M9: =IF(ISNA(C10),"NULL","NOT NULL") -> NOT NULL | N9: =COUNTIF(A:A,A9) -> 1 | O9: =IF(ISNA(VLOOKUP(J9,Vendors!A:A,1,FALSE)),"MISSING VENDER","VALID") -> VALID | P9: =IF(ISNA(VLOOKUP(H9,'Customers'!A:A,1,FALSE)),"missing customer ","valid") -> missing customer | Q9: =IF(ISBLANK(D9),"INVALID","VALID") -> VALID | R9: =IF(ISNA(F9),"INVALID","VALID") -> VALID
A10: TRX100008 | B10: 44775 | C10: 136347.73 | D10: Revenue | E10: Product | F10: Retail | G10: West | H10: CUST10168 | I10: =_xlfn.XLOOKUP(H10,'Customers'!A10:A409,'Customers'!B10:B409," ") -> Sparks, Kent and Anderson | K10: Poor similar feeling close require probably rather thought. | L10: =IF(ISERROR(B10),"ERORROR","OK") -> OK | M10: =IF(ISNA(C11),"NULL","NOT NULL") -> NOT NULL | N10: =COUNTIF(A:A,A10) -> 1 | O10: =IF(ISNA(VLOOKUP(J10,Vendors!A:A,1,FALSE)),"MISSING VENDER","VALID") -> MISSING VENDER | P10: =IF(ISNA(VLOOKUP(H10,'Customers'!A:A,1,FALSE)),"missing customer ","valid") -> valid | Q10: =IF(ISBLANK(D10),"INVALID","VALID") -> VALID | R10: =IF(ISNA(F10),"INVALID","VALID") -> VALID
A11: TRX100009 | B11: 45094 | C11: 159482 | D11: Revenue | E11: Product | F11: Retail | G11: West | H11: CUST10151 | I11: =_xlfn.XLOOKUP(H11,'Customers'!A11:A410,'Customers'!B11:B410," ") -> Horn, Henry and Walter | K11: Cause worker statement office able foot. | L11: =IF(ISERROR(B11),"ERORROR","OK") -> OK | M11: =IF(ISNA(C12),"NULL","NOT NULL") -> NOT NULL | N11: =COUNTIF(A:A,A11) -> 1 | O11: =IF(ISNA(VLOOKUP(J11,Vendors!A:A,1,FALSE)),"MISSING VENDER","VALID") -> MISSING VENDER | P11: =IF(ISNA(VLOOKUP(H11,'Customers'!A:A,1,FALSE)),"missing customer ","valid") -> valid | Q11: =IF(ISBLANK(D11),"INVALID","VALID") -> VALID | R11: =IF(ISNA(F11),"INVALID","VALID") -> VALID
A12: TRX100010 | B12: 44749 | C12: 15882.36 | D12: Equity | E12: Equity | F12: Retail | G12: South | I12: =_xlfn.XLOOKUP(H12,'Customers'!A12:A411,'Customers'!B12:B411," ") | K12: Ready enter quite attack resource list commercial. | L12: =IF(ISERROR(B12),"ERORROR","OK") -> OK | M12: =IF(ISNA(C13),"NULL","NOT NULL") -> NOT NULL | N12: =COUNTIF(A:A,A12) -> 1 | O12: =IF(ISNA(VLOOKUP(J12,Vendors!A:A,1,FALSE)),"MISSING VENDER","VALID") -> MISSING VENDER | P12: =IF(ISNA(VLOOKUP(H12,'Customers'!A:A,1,FALSE)),"missing customer ","valid") -> missing customer | Q12: =IF(ISBLANK(D12),"INVALID","VALID") -> VALID | R12: =IF(ISNA(F12),"INVALID","VALID") -> VALID
A13: TRX100011 | B13: 44781 | C13: 217487.82 | D13: Revenue | E13: Product | F13: Online | G13: North | H13: CUST10353 | I13: =_xlfn.XLOOKUP(H13,'Customers'!A13:A412,'Customers'!B13:B412," ") -> Santiago-Gray | K13: Before green media feeling Mr half trouble. | L13: =IF(ISERROR(B13),"ERORROR","OK") -> OK | M13: =IF(ISNA(C14),"NULL","NOT NULL") -> NOT NULL | N13: =COUNTIF(A:A,A13) -> 1 | O13: =IF(ISNA(VLOOKUP(J13,Vendors!A:A,1,FALSE)),"MISSING VENDER","VALID") -> MISSING VENDER | P13: =IF(ISNA(VLOOKUP(H13,'Customers'!A:A,1,FALSE)),"missing customer ","valid") -> valid | Q13: =IF(ISBLANK(D13),"INVALID","VALID") -> VALID | R13: =IF(ISNA(F13),"INVALID","VALID") -> VALID
A14: TRX100012 | B14: 45001 | C14: -8913.27 | D14: Expense | E14: Other | F14: Enterprise | G14: East | I14: =_xlfn.XLOOKUP(H14,'Customers'!A14:A413,'Customers'!B14:B413," ") | J14: VEND1067 | K14: Rise discover visit security end buy medical think. | L14: =IF(ISERROR(B14),"ERORROR","OK") -> OK | M14: =IF(ISNA(C15),"NULL","NOT NULL") -> NOT NULL | N14: =COUNTIF(A:A,A14) -> 1 | O14: =IF(ISNA(VLOOKUP(J14,Vendors!A:A,1,FALSE)),"MISSING VENDER","VALID") -> VALID | P14: =IF(ISNA(VLOOKUP(H14,'Customers'!A:A,1,FALSE)),"missing customer ","valid") -> missing customer | Q14: =IF(ISBLANK(D14),"INVALID","VALID") -> VALID | R14: =IF(ISNA(F14),"INVALID","VALID") -> VALID
A15: TRX100013 | B15: 45270 | C15: 139523.96 | D15: Revenue | E15: Service | F15: Retail | G15: North | H15: CUST10243 | I15: =_xlfn.XLOOKUP(H15,'Customers'!A15:A414,'Customers'!B15:B414," ") -> Sosa Inc | K15: Military line exist little education family world. | L15: =IF(ISERROR(B15),"ERORROR","OK") -> OK | M15: =IF(ISNA(C16),"NULL","NOT NULL") -> NOT NULL | N15: =COUNTIF(A:A,A15) -> 1 | O15: =IF(ISNA(VLOOKUP(J15,Vendors!A:A,1,FALSE)),"MISSING VENDER","VALID") -> MISSING VENDER | P15: =IF(ISNA(VLOOKUP(H15,'Customers'!A:A,1,FALSE)),"missing customer ","valid") -> valid | Q15: =IF(ISBLANK(D15),"INVALID","VALID") -> VALID | R15: =IF(ISNA(F15),"INVALID","VALID") -> VALID
A16: TRX100014 | B16: 45125 | C16: 165589.04 | D16: Revenue | E16: Service | F16: Online | G16: East | H16: CUST10357 | I16: =_xlfn.XLOOKUP(H16,'Customers'!A16:A415,'Customers'!B16:B415," ") -> Webb Ltd | K16: Artist place loss morning. | L16: =IF(ISERROR(B16),"ERORROR","OK") -> OK | M16: =IF(ISNA(C17),"NULL","NOT NULL") -> NOT NULL | N16: =COUNTIF(A:A,A16) -> 1 | O16: =IF(ISNA(VLOOKUP(J16,Vendors!A:A,1,FALSE)),"MISSING VENDER","VALID") -> MISSING VENDER | P16: =IF(ISNA(VLOOKUP(H16,'Customers'!A:A,1,FALSE)),"missing customer ","valid") -> valid | Q16: =IF(ISBLANK(D16),"INVALID","VALID") -> VALID | R16: =IF(ISNA(F16),"INVALID","VALID") -> VALID
A17: TRX100015 | B17: 44952 | C17: 262541.15 | D17: Revenue | E17: Service | F17: Retail | G17: West | H17: CUST10045 | I17: =_xlfn.XLOOKUP(H17,'Customers'!A17:A416,'Customers'!B17:B416," ") -> Curry, Owens and Carter | K17: Game evidence support skill pretty. | L17: =IF(ISERROR(B17),"ERORROR","OK") -> OK | M17: =IF(ISNA(C18),"NULL","NOT NULL") -> NOT NULL | N17: =COUNTIF(A:A,A17) -> 1 | O17: =IF(ISNA(VLOOKUP(J17,Vendors!A:A,1,FALSE)),"MISSING VENDER","VALID") -> MISSING VENDER | P17: =IF(ISNA(VLOOKUP(H17,'Customers'!A:A,1,FALSE)),"missing customer ","valid") -> valid | Q17: =IF(ISBLANK(D17),"INVALID","VALID") -> VALID | R17: =IF(ISNA(F17),"INVALID","VALID") -> VALID
A18: TRX100016 | B18: 45087 | C18: 152113.39 | D18: Revenue | E18: Service | F18: Online | G18: South | H18: CUST10120 | I18: =_xlfn.XLOOKUP(H18,'Customers'!A18:A417,'Customers'!B18:B417," ") -> Richardson Ltd | K18: Bad author generation decade increase. | L18: =IF(ISERROR(B18),"ERORROR","OK") -> OK | M18: =IF(ISNA(C19),"NULL","NOT NULL") -> NOT NULL | N18: =COUNTIF(A:A,A18) -> 1 | O18: =IF(ISNA(VLOOKUP(J18,Vendors!A:A,1,FALSE)),"MISSING VENDER","VALID") -> MISSING VENDER | P18: =IF(ISNA(VLOOKUP(H18,'Customers'!A:A,1,FALSE)),"missing customer ","valid") -> valid | Q18: =IF(ISBLANK(D18),"INVALID","VALID") -> VALID | R18: =IF(ISNA(F18),"INVALID","VALID") -> VALID
A19: TRX100017 | B19: 44726 | C19: 107495.7 | D19: Revenue | E19: Service | F19: Online | G19: North | H19: CUST10228 | I19: =_xlfn.XLOOKUP(H19,'Customers'!A19:A418,'Customers'!B19:B418," ") -> Newton and Sons | K19: Left own eat wife tell with. | L19: =IF(ISERROR(B19),"ERORROR","OK") -> OK | M19: =IF(ISNA(C20),"NULL","NOT NULL") -> NOT NULL | N19: =COUNTIF(A:A,A19) -> 1 | O19: =IF(ISNA(VLOOKUP(J19,Vendors!A:A,1,FALSE)),"MISSING VENDER","VALID") -> MISSING VENDER | P19: =IF(ISNA(VLOOKUP(H19,'Customers'!A:A,1,FALSE)),"missing customer ","valid") -> valid | Q19: =IF(ISBLANK(D19),"INVALID","VALID") -> VALID | R19: =IF(ISNA(F19),"INVALID","VALID") -> VALID
A20: TRX100018 | B20: 45190 | C20: 83127.62 | D20: Revenue | E20: Subscription | F20: Online | G20: West | H20: CUST10333 | I20: =_xlfn.XLOOKUP(H20,'Customers'!A20:A419,'Customers'!B20:B419," ") -> Frank, Webster and Ferguson | K20: Individual first region. | L20: =IF(ISERROR(B20),"ERORROR","OK") -> OK | M20: =IF(ISNA(C21),"NULL","NOT NULL") -> NOT NULL | N20: =COUNTIF(A:A,A20) -> 1 | O20: =IF(ISNA(VLOOKUP(J20,Vendors!A:A,1,FALSE)),"MISSING VENDER","VALID") -> MISSING VENDER | P20: =IF(ISNA(VLOOKUP(H20,'Customers'!A:A,1,FALSE)),"missing customer ","valid") -> valid | Q20: =IF(ISBLANK(D20),"INVALID","VALID") -> VALID | R20: =IF(ISNA(F20),"INVALID","VALID") -> VALID
A21: TRX100019 | B21: 44793 | C21: 145634.47 | D21: Revenue | E21: Service | F21: Enterprise | G21: West | H21: CUST10302 | I21: =_xlfn.XLOOKUP(H21,'Customers'!A21:A420,'Customers'!B21:B420," ") -> Contreras, Bell and Torres | K21: Rise war shake doctor. | L21: =IF(ISERROR(B21),"ERORROR","OK") -> OK | M21: =IF(ISNA(C22),"NULL","NOT NULL") -> NOT NULL | N21: =COUNTIF(A:A,A21) -> 1 | O21: =IF(ISNA(VLOOKUP(J21,Vendors!A:A,1,FALSE)),"MISSING VENDER","VALID") -> MISSING VENDER | P21: =IF(ISNA(VLOOKUP(H21,'Customers'!A:A,1,FALSE)),"missing customer ","valid") -> valid | Q21: =IF(ISBLANK(D21),"INVALID","VALID") -> VALID | R21: =IF(ISNA(F21),"INVALID","VALID") -> VALID
A22: TRX100020 | B22: 45062 | C22: 167566.97 | D22: Revenue | E22: Service | F22: Retail | G22: North | H22: CUST10042 | I22: =_xlfn.XLOOKUP(H22,'Customers'!A22:A421,'Customers'!B22:B421," ") -> Smith, Coleman and Ortiz | K22: Before expect allow job one set. | L22: =IF(ISERROR(B22),"ERORROR","OK") -> OK | M22: =IF(ISNA(C23),"NULL","NOT NULL") -> NOT NULL | N22: =COUNTIF(A:A,A22) -> 1 | O22: =IF(ISNA(VLOOKUP(J22,Vendors!A:A,1,FALSE)),"MISSING VENDER","VALID") -> MISSING VENDER | P22: =IF(ISNA(VLOOKUP(H22,'Customers'!A:A,1,FALSE)),"missing customer ","valid") -> valid | Q22: =IF(ISBLANK(D22),"INVALID","VALID") -> VALID | R22: =IF(ISNA(F22),"INVALID","VALID") -> VALID
A23: TRX100021 | B23: 44726 | C23: -2000 | D23: Expense | E23: Rent | F23: Online | G23: West | I23: =_xlfn.XLOOKUP(H23,'Customers'!A23:A422,'Customers'!B23:B422," ") | J23: VEND1022 | K23: Side official leave seem financial. | L23: =IF(ISERROR(B23),"ERORROR","OK") -> OK | M23: =IF(ISNA(C24),"NULL","NOT NULL") -> NOT NULL | N23: =COUNTIF(A:A,A23) -> 1 | O23: =IF(ISNA(VLOOKUP(J23,Vendors!A:A,1,FALSE)),"MISSING VENDER","VALID") -> VALID | P23: =IF(ISNA(VLOOKUP(H23,'Customers'!A:A,1,FALSE)),"missing customer ","valid") -> missing customer | Q23: =IF(ISBLANK(D23),"INVALID","VALID") -> VALID | R23: =IF(ISNA(F23),"INVALID","VALID") -> VALID
A24: TRX100022 | B24: 44998 | C24: 203374.65 | D24: Revenue | E24: Service | F24: Online | G24: South | H24: CUST10021 | I24: =_xlfn.XLOOKUP(H24,'Customers'!A24:A423,'Customers'!B24:B423," ") | K24: Must require bit relate Congress local improve organization. | L24: =IF(ISERROR(B24),"ERORROR","OK") -> OK | M24: =IF(ISNA(C25),"NULL","NOT NULL") -> NOT NULL | N24: =COUNTIF(A:A,A24) -> 1 | O24: =IF(ISNA(VLOOKUP(J24,Vendors!A:A,1,FALSE)),"MISSING VENDER","VALID") -> MISSING VENDER | P24: =IF(ISNA(VLOOKUP(H24,'Customers'!A:A,1,FALSE)),"missing customer ","valid") -> valid | Q24: =IF(ISBLANK(D24),"INVALID","VALID") -> VALID | R24: =IF(ISNA(F24),"INVALID","VALID") -> VALID
A25: TRX100023 | B25: 45189 | C25: 171433.19 | D25: Revenue | E25: Product | F25: Enterprise | G25: West | H25: CUST10218 | I25: =_xlfn.XLOOKUP(H25,'Customers'!A25:A424,'Customers'!B25:B424," ") -> Jones-Gomez | K25: Identify loss across fact government sea upon. | L25: =IF(ISERROR(B25),"ERORROR","OK") -> OK | M25: =IF(ISNA(C26),"NULL","NOT NULL") -> NOT NULL | N25: =COUNTIF(A:A,A25) -> 1 | O25: =IF(ISNA(VLOOKUP(J25,Vendors!A:A,1,FALSE)),"MISSING VENDER","VALID") -> MISSING VENDER | P25: =IF(ISNA(VLOOKUP(H25,'Customers'!A:A,1,FALSE)),"missing customer ","valid") -> valid | Q25: =IF(ISBLANK(D25),"INVALID","VALID") -> VALID | R25: =IF(ISNA(F25),"INVALID","VALID") -> VALID
A26: TRX100024 | B26: 44850 | C26: -60198.87 | D26: Expense | E26: Payroll | F26: Enterprise | G26: North | I26: =_xlfn.XLOOKUP(H26,'Customers'!A26:A425,'Customers'!B26:B425," ") | J26: VEND1058 | K26: Big fine cause full reality heart condition another. | L26: =IF(ISERROR(B26),"ERORROR","OK") -> OK | M26: =IF(ISNA(C27),"NULL","NOT NULL") -> NOT NULL | N26: =COUNTIF(A:A,A26) -> 1 | O26: =IF(ISNA(VLOOKUP(J26,Vendors!A:A,1,FALSE)),"MISSING VENDER","VALID") -> VALID | P26: =IF(ISNA(VLOOKUP(H26,'Customers'!A:A,1,FALSE)),"missing customer ","valid") -> missing customer | Q26: =IF(ISBLANK(D26),"INVALID","VALID") -> VALID | R26: =IF(ISNA(F26),"INVALID","VALID") -> VALID
A27: TRX100025 | B27: 45097 | C27: -40143.88 | D27: Expense | E27: Rent | F27: Retail | G27: West | I27: =_xlfn.XLOOKUP(H27,'Customers'!A27:A426,'Customers'!B27:B426," ") | J27: VEND1037 | K27: Good owner financial any result summer physical. | L27: =IF(ISERROR(B27),"ERORROR","OK") -> OK | M27: =IF(ISNA(C28),"NULL","NOT NULL") -> NOT NULL | N27: =COUNTIF(A:A,A27) -> 1 | O27: =IF(ISNA(VLOOKUP(J27,Vendors!A:A,1,FALSE)),"MISSING VENDER","VALID") -> VALID | P27: =IF(ISNA(VLOOKUP(H27,'Customers'!A:A,1,FALSE)),"missing customer ","valid") -> missing customer | Q27: =IF(ISBLANK(D27),"INVALID","VALID") -> VALID | R27: =IF(ISNA(F27),"INVALID","VALID") -> VALID
A28: TRX100026 | B28: 45208 | C28: -38329 | D28: Expense | E28: Marketing | F28: Enterprise | G28: West | I28: =_xlfn.XLOOKUP(H28,'Customers'!A28:A427,'Customers'!B28:B427," ") | J28: VEND1049 | K28: Sport note decide who modern car knowledge. | L28: =IF(ISERROR(B28),"ERORROR","OK") -> OK | M28: =IF(ISNA(C29),"NULL","NOT NULL") -> NOT NULL | N28: =COUNTIF(A:A,A28) -> 1 | O28: =IF(ISNA(VLOOKUP(J28,Vendors!A:A,1,FALSE)),"MISSING VENDER","VALID") -> VALID | P28: =IF(ISNA(VLOOKUP(H28,'Customers'!A:A,1,FALSE)),"missing customer ","valid") -> missing customer | Q28: =IF(ISBLANK(D28),"INVALID","VALID") -> VALID | R28: =IF(ISNA(F28),"INVALID","VALID") -> VALID
A29: TRX100027 | B29: 44901 | C29: 193475.45 | D29: Revenue | E29: Service | F29: Retail | G29: South | H29: CUST10146 | I29: =_xlfn.XLOOKUP(H29,'Customers'!A29:A428,'Customers'!B29:B428," ") -> Ward, Barber and Ruiz | K29: Game step assume late home order morning to. | L29: =IF(ISERROR(B29),"ERORROR","OK") -> OK | M29: =IF(ISNA(C30),"NULL","NOT NULL") -> NOT NULL | N29: =COUNTIF(A:A,A29) -> 1 | O29: =IF(ISNA(VLOOKUP(J29,Vendors!A:A,1,FALSE)),"MISSING VENDER","VALID") -> MISSING VENDER | P29: =IF(ISNA(VLOOKUP(H29,'Customers'!A:A,1,FALSE)),"missing customer ","valid") -> valid | Q29: =IF(ISBLANK(D29),"INVALID","VALID") -> VALID | R29: =IF(ISNA(F29),"INVALID","VALID") -> VALID
A30: TRX100028 | B30: 45002 | C30: 139672.98 | D30: Revenue | E30: Subscription | F30: Enterprise | G30: South | H30: CUST10074 | I30: =_xlfn.XLOOKUP(H30,'Customers'!A30:A429,'Customers'!B30:B429," ") -> Mccarthy, Hernandez and May | K30: Nature need environment operation country easy across choice. | L30: =IF(ISERROR(B30),"ERORROR","OK") -> OK | M30: =IF(ISNA(C31),"NULL","NOT NULL") -> NOT NULL | N30: =COUNTIF(A:A,A30) -> 1 | O30: =IF(ISNA(VLOOKUP(J30,Vendors!A:A,1,FALSE)),"MISSING VENDER","VALID") -> MISSING VENDER | P30: =IF(ISNA(VLOOKUP(H30,'Customers'!A:A,1,FALSE)),"missing customer ","valid") -> valid | Q30: =IF(ISBLANK(D30),"INVALID","VALID") -> VALID | R30: =IF(ISNA(F30),"INVALID","VALID") -> VALID
A31: TRX100029 | B31: 45188 | C31: 198385.78 | D31: Revenue | E31: Subscription | F31: Enterprise | G31: North | H31: CUST10011 | I31: =_xlfn.XLOOKUP(H31,'Customers'!A31:A430,'Customers'!B31:B430," ") | K31: Scientist particularly include true listen happy. | L31: =IF(ISERROR(B31),"ERORROR","OK") -> OK | M31: =IF(ISNA(C32),"NULL","NOT NULL") -> NOT NULL | N31: =COUNTIF(A:A,A31) -> 1 | O31: =IF(ISNA(VLOOKUP(J31,Vendors!A:A,1,FALSE)),"MISSING VENDER","VALID") -> MISSING VENDER | P31: =IF(ISNA(VLOOKUP(H31,'Customers'!A:A,1,FALSE)),"missing customer ","valid") -> valid | Q31: =IF(ISBLANK(D31),"INVALID","VALID") -> VALID | R31: =IF(ISNA(F31),"INVALID","VALID") -> VALID
A32: TRX100030 | B32: 44814 | C32: 137108.16 | D32: Revenue | E32: Service | F32: Enterprise | G32: East | H32: CUST10325 | I32: =_xlfn.XLOOKUP(H32,'Customers'!A32:A431,'Customers'!B32:B431," ") -> Horton Group | K32: Citizen help never simple course. | L32: =IF(ISERROR(B32),"ERORROR","OK") -> OK | M32: =IF(ISNA(C33),"NULL","NOT NULL") -> NOT NULL | N32: =COUNTIF(A:A,A32) -> 1 | O32: =IF(ISNA(VLOOKUP(J32,Vendors!A:A,1,FALSE)),"MISSING VENDER","VALID") -> MISSING VENDER | P32: =IF(ISNA(VLOOKUP(H32,'Customers'!A:A,1,FALSE)),"missing customer ","valid") -> valid | Q32: =IF(ISBLANK(D32),"INVALID","VALID") -> VALID | R32: =IF(ISNA(F32),"INVALID","VALID") -> VALID
A33: TRX100031 | B33: 44624 | C33: -44326.21 | D33: Expense | E33: Other | F33: Retail | G33: East | I33: =_xlfn.XLOOKUP(H33,'Customers'!A33:A432,'Customers'!B33:B432," ") | J33: VEND1053 | K33: Billion newspaper modern fine career somebody. | L33: =IF(ISERROR(B33),"ERORROR","OK") -> OK | M33: =IF(ISNA(C34),"NULL","NOT NULL") -> NOT NULL | N33: =COUNTIF(A:A,A33) -> 1 | O33: =IF(ISNA(VLOOKUP(J33,Vendors!A:A,1,FALSE)),"MISSING VENDER","VALID") -> VALID | P33: =IF(ISNA(VLOOKUP(H33,'Customers'!A:A,1,FALSE)),"missing customer ","valid") -> missing customer | Q33: =IF(ISBLANK(D33),"INVALID","VALID") -> VALID | R33: =IF(ISNA(F33),"INVALID","VALID") -> VALID
A34: TRX100032 | B34: 44970 | C34: 162088.99 | D34: Revenue | E34: Service | F34: Enterprise | G34: North | H34: CUST10203 | I34: =_xlfn.XLOOKUP(H34,'Customers'!A34:A433,'Customers'!B34:B433," ") -> Fry-Turner | K34: Wall campaign might anyone. | L34: =IF(ISERROR(B34),"ERORROR","OK") -> OK | M34: =IF(ISNA(C35),"NULL","NOT NULL") -> NOT NULL | N34: =COUNTIF(A:A,A34) -> 1 | O34: =IF(ISNA(VLOOKUP(J34,Vendors!A:A,1,FALSE)),"MISSING VENDER","VALID") -> MISSING VENDER | P34: =IF(ISNA(VLOOKUP(H34,'Customers'!A:A,1,FALSE)),"missing customer ","valid") -> valid | Q34: =IF(ISBLANK(D34),"INVALID","VALID") -> VALID | R34: =IF(ISNA(F34),"INVALID","VALID") -> VALID
A35: TRX100033 | B35: 44847 | C35: 138103.68 | D35: Revenue | E35: Subscription | F35: Online | G35: North | H35: CUST10151 | I35: =_xlfn.XLOOKUP(H35,'Customers'!A35:A434,'Customers'!B35:B434," ") -> Horn, Henry and Walter | K35: Could impact decide key. | L35: =IF(ISERROR(B35),"ERORROR","OK") -> OK | M35: =IF(ISNA(C36),"NULL","NOT NULL") -> NOT NULL | N35: =COUNTIF(A:A,A35) -> 1 | O35: =IF(ISNA(VLOOKUP(J35,Vendors!A:A,1,FALSE)),"MISSING VENDER","VALID") -> MISSING VENDER | P35: =IF(ISNA(VLOOKUP(H35,'Customers'!A:A,1,FALSE)),"missing customer ","valid") -> valid | Q35: =IF(ISBLANK(D35),"INVALID","VALID") -> VALID | R35: =IF(ISNA(F35),"INVALID","VALID") -> VALID
A36: TRX100034 | B36: 44695 | C36: -10197.61 | D36: Expense | E36: Utilities | F36: Retail | G36: East | I36: =_xlfn.XLOOKUP(H36,'Customers'!A36:A435,'Customers'!B36:B435," ") | J36: VEND1014 | K36: Imagine must who discover since painting. | L36: =IF(ISERROR(B36),"ERORROR","OK") -> OK | M36: =IF(ISNA(C37),"NULL","NOT NULL") -> NOT NULL | N36: =COUNTIF(A:A,A36) -> 1 | O36: =IF(ISNA(VLOOKUP(J36,Vendors!A:A,1,FALSE)),"MISSING VENDER","VALID") -> VALID | P36: =IF(ISNA(VLOOKUP(H36,'Customers'!A:A,1,FALSE)),"missing customer ","valid") -> missing customer | Q36: =IF(ISBLANK(D36),"INVALID","VALID") -> VALID | R36: =IF(ISNA(F36),"INVALID","VALID") -> VALID
A37: TRX100035 | B37: 45145 | C37: -62926.94 | D37: Expense | E37: Marketing | F37: Retail | G37: West | I37: =_xlfn.XLOOKUP(H37,'Customers'!A37:A436,'Customers'!B37:B436," ") | J37: VEND1093 | K37: Training nor arrive. | L37: =IF(ISERROR(B37),"ERORROR","OK") -> OK | M37: =IF(ISNA(C38),"NULL","NOT NULL") -> NOT NULL | N37: =COUNTIF(A:A,A37) -> 1 | O37: =IF(ISNA(VLOOKUP(J37,Vendors!A:A,1,FALSE)),"MISSING VENDER","VALID") -> VALID | P37: =IF(ISNA(VLOOKUP(H37,'Customers'!A:A,1,FALSE)),"missing customer ","valid") -> missing customer | Q37: =IF(ISBLANK(D37),"INVALID","VALID") -> VALID | R37: =IF(ISNA(F37),"INVALID","VALID") -> VALID
A38: TRX100036 | B38: 45195 | C38: 144593.87 | D38: Revenue | E38: Service | F38: Enterprise | G38: East | H38: CUST10086 | I38: =_xlfn.XLOOKUP(H38,'Customers'!A38:A437,'Customers'!B38:B437," ") -> Harris LLC | K38: Field some arrive society everybody guy public. | L38: =IF(ISERROR(B38),"ERORROR","OK") -> OK | M38: =IF(ISNA(C39),"NULL","NOT NULL") -> NOT NULL | N38: =COUNTIF(A:A,A38) -> 1 | O38: =IF(ISNA(VLOOKUP(J38,Vendors!A:A,1,FALSE)),"MISSING VENDER","VALID") -> MISSING VENDER | P38: =IF(ISNA(VLOOKUP(H38,'Customers'!A:A,1,FALSE)),"missing customer ","valid") -> valid | Q38: =IF(ISBLANK(D38),"INVALID","VALID") -> VALID | R38: =IF(ISNA(F38),"INVALID","VALID") -> VALID
A39: TRX100037 | B39: 44595 | C39: 38814.58 | D39: Revenue | E39: Product | F39: Retail | G39: North | H39: CUST10013 | I39: =_xlfn.XLOOKUP(H39,'Customers'!A39:A438,'Customers'!B39:B438," ") | K39: Order agreement mind everything. | L39: =IF(ISERROR(B39),"ERORROR","OK") -> OK | M39: =IF(ISNA(C40),"NULL","NOT NULL") -> NOT NULL | N39: =COUNTIF(A:A,A39) -> 1 | O39: =IF(ISNA(VLOOKUP(J39,Vendors!A:A,1,FALSE)),"MISSING VENDER","VALID") -> MISSING VENDER | P39: =IF(ISNA(VLOOKUP(H39,'Customers'!A:A,1,FALSE)),"missing customer ","valid") -> valid | Q39: =IF(ISBLANK(D39),"INVALID","VALID") -> VALID | R39: =IF(ISNA(F39),"INVALID","VALID") -> VALID
A40: TRX100038 | B40: 44983 | C40: -36977.97 | D40: Expense | E40: Rent | F40: Online | G40: East | I40: =_xlfn.XLOOKUP(H40,'Customers'!A40:A439,'Customers'!B40:B439," ") | J40: VEND1082 | K40: Watch would miss interview water trouble. | L40: =IF(ISERROR(B40),"ERORROR","OK") -> OK | M40: =IF(ISNA(C41),"NULL","NOT NULL") -> NOT NULL | N40: =COUNTIF(A:A,A40) -> 1 | O40: =IF(ISNA(VLOOKUP(J40,Vendors!A:A,1,FALSE)),"MISSING VENDER","VALID") -> VALID | P40: =IF(ISNA(VLOOKUP(H40,'Customers'!A:A,1,FALSE)),"missing customer ","valid") -> missing customer | Q40: =IF(ISBLANK(D40),"INVALID","VALID") -> VALID | R40: =IF(ISNA(F40),"INVALID","VALID") -> VALID
A41: TRX100039 | B41: 44914 | C41: -18304.84 | D41: Expense | E41: Payroll | F41: Enterprise | G41: East | I41: =_xlfn.XLOOKUP(H41,'Customers'!A41:A440,'Customers'!B41:B440," ") | J41: VEND1106 | K41: Save in thing model. | L41: =IF(ISERROR(B41),"ERORROR","OK") -> OK | M41: =IF(ISNA(C42),"NULL","NOT NULL") -> NOT NULL | N41: =COUNTIF(A:A,A41) -> 1 | O41: =IF(ISNA(VLOOKUP(J41,Vendors!A:A,1,FALSE)),"MISSING VENDER","VALID") -> VALID | P41: =IF(ISNA(VLOOKUP(H41,'Customers'!A:A,1,FALSE)),"missing customer ","valid") -> missing customer | Q41: =IF(ISBLANK(D41),"INVALID","VALID") -> VALID | R41: =IF(ISNA(F41),"INVALID","VALID") -> VALID
A42: TRX100040 | B42: 45228 | C42: 248459.88 | D42: Revenue | E42: Subscription | F42: Online | G42: East | H42: CUST10022 | I42: =_xlfn.XLOOKUP(H42,'Customers'!A42:A441,'Customers'!B42:B441," ") | K42: Defense argue help someone action throw. | L42: =IF(ISERROR(B42),"ERORROR","OK") -> OK | M42: =IF(ISNA(C43),"NULL","NOT NULL") -> NOT NULL | N42: =COUNTIF(A:A,A42) -> 1 | O42: =IF(ISNA(VLOOKUP(J42,Vendors!A:A,1,FALSE)),"MISSING VENDER","VALID") -> MISSING VENDER | P42: =IF(ISNA(VLOOKUP(H42,'Customers'!A:A,1,FALSE)),"missing customer ","valid") -> valid | Q42: =IF(ISBLANK(D42),"INVALID","VALID") -> VALID | R42: =IF(ISNA(F42),"INVALID","VALID") -> VALID
A43: TRX100041 | B43: 44838 | C43: 120099.72 | D43: Revenue | E43: Product | F43: Online | G43: East | H43: CUST10128 | I43: =_xlfn.XLOOKUP(H43,'Customers'!A43:A442,'Customers'!B43:B442," ") -> Webb, Hancock and Fisher | K43: Reduce suddenly against ball medical. | L43: =IF(ISERROR(B43),"ERORROR","OK") -> OK | M43: =IF(ISNA(C44),"NULL","NOT NULL") -> NOT NULL | N43: =COUNTIF(A:A,A43) -> 1 | O43: =IF(ISNA(VLOOKUP(J43,Vendors!A:A,1,FALSE)),"MISSING VENDER","VALID") -> MISSING VENDER | P43: =IF(ISNA(VLOOKUP(H43,'Customers'!A:A,1,FALSE)),"missing customer ","valid") -> valid | Q43: =IF(ISBLANK(D43),"INVALID","VALID") -> VALID | R43: =IF(ISNA(F43),"INVALID","VALID") -> VALID
A44: TRX100042 | B44: 44888 | C44: -39571.02 | D44: Expense | E44: Other | F44: Online | G44: South | I44: =_xlfn.XLOOKUP(H44,'Customers'!A44:A443,'Customers'!B44:B443," ") | J44: VEND1063 | K44: Far make skill lose audience art. | L44: =IF(ISERROR(B44),"ERORROR","OK") -> OK | M44: =IF(ISNA(C45),"NULL","NOT NULL") -> NOT NULL | N44: =COUNTIF(A:A,A44) -> 1 | O44: =IF(ISNA(VLOOKUP(J44,Vendors!A:A,1,FALSE)),"MISSING VENDER","VALID") -> VALID | P44: =IF(ISNA(VLOOKUP(H44,'Customers'!A:A,1,FALSE)),"missing customer ","valid") -> missing customer | Q44: =IF(ISBLANK(D44),"INVALID","VALID") -> VALID | R44: =IF(ISNA(F44),"INVALID","VALID") -> VALID
A45: TRX100043 | B45: 45033 | C45: 79909.54 | D45: Revenue | E45: Subscription | F45: Retail | G45: East | H45: CUST10251 | I45: =_xlfn.XLOOKUP(H45,'Customers'!A45:A444,'Customers'!B45:B444," ") -> Graham LLC | K45: Tax north line it fund describe. | L45: =IF(ISERROR(B45),"ERORROR","OK") -> OK | M45: =IF(ISNA(C46),"NULL","NOT NULL") -> NOT NULL | N45: =COUNTIF(A:A,A45) -> 1 | O45: =IF(ISNA(VLOOKUP(J45,Vendors!A:A,1,FALSE)),"MISSING VENDER","VALID") -> MISSING VENDER | P45: =IF(ISNA(VLOOKUP(H45,'Customers'!A:A,1,FALSE)),"missing customer ","valid") -> valid | Q45: =IF(ISBLANK(D45),"INVALID","VALID") -> VALID | R45: =IF(ISNA(F45),"INVALID","VALID") -> VALID
A46: TRX100044 | B46: 44977 | C46: -50444.36 | D46: Expense | E46: Other | F46: Enterprise | G46: North | I46: =_xlfn.XLOOKUP(H46,'Customers'!A46:A445,'Customers'!B46:B445," ") | J46: VEND1020 | K46: Follow put campaign lose summer lot if others. | L46: =IF(ISERROR(B46),"ERORROR","OK") -> OK | M46: =IF(ISNA(C47),"NULL","NOT NULL") -> NOT NULL | N46: =COUNTIF(A:A,A46) -> 1 | O46: =IF(ISNA(VLOOKUP(J46,Vendors!A:A,1,FALSE)),"MISSING VENDER","VALID") -> VALID | P46: =IF(ISNA(VLOOKUP(H46,'Customers'!A:A,1,FALSE)),"missing customer ","valid") -> missing customer | Q46: =IF(ISBLANK(D46),"INVALID","VALID") -> VALID | R46: =IF(ISNA(F46),"INVALID","VALID") -> VALID
A47: TRX100045 | B47: 44879 | C47: -22716.39 | D47: Expense | E47: Supplies | F47: Retail | G47: East | I47: =_xlfn.XLOOKUP(H47,'Customers'!A47:A446,'Customers'!B47:B446," ") | J47: VEND1062 | K47: Structure have effect. | L47: =IF(ISERROR(B47),"ERORROR","OK") -> OK | M47: =IF(ISNA(C48),"NULL","NOT NULL") -> NOT NULL | N47: =COUNTIF(A:A,A47) -> 1 | O47: =IF(ISNA(VLOOKUP(J47,Vendors!A:A,1,FALSE)),"MISSING VENDER","VALID") -> VALID | P47: =IF(ISNA(VLOOKUP(H47,'Customers'!A:A,1,FALSE)),"missing customer ","valid") -> missing customer | Q47: =IF(ISBLANK(D47),"INVALID","VALID") -> VALID | R47: =IF(ISNA(F47),"INVALID","VALID") -> VALID
A48: TRX100046 | B48: 44934 | C48: -14936.32 | D48: Expense | E48: Marketing | F48: Online | G48: East | I48: =_xlfn.XLOOKUP(H48,'Customers'!A48:A447,'Customers'!B48:B447," ") | J48: VEND1025 | K48: Second get its since return. | L48: =IF(ISERROR(B48),"ERORROR","OK") -> OK | M48: =IF(ISNA(C49),"NULL","NOT NULL") -> NOT NULL | N48: =COUNTIF(A:A,A48) -> 1 | O48: =IF(ISNA(VLOOKUP(J48,Vendors!A:A,1,FALSE)),"MISSING VENDER","VALID") -> VALID | P48: =IF(ISNA(VLOOKUP(H48,'Customers'!A:A,1,FALSE)),"missing customer ","valid") -> missing customer | Q48: =IF(ISBLANK(D48),"INVALID","VALID") -> VALID | R48: =IF(ISNA(F48),"INVALID","VALID") -> VALID
A49: TRX100047 | B49: 45199 | C49: 141946.92 | D49: Revenue | E49: Service | F49: Retail | G49: West | H49: CUST10342 | I49: =_xlfn.XLOOKUP(H49,'Customers'!A49:A448,'Customers'!B49:B448," ") -> Guzman, Kelly and Marshall | K49: Then section each support majority. | L49: =IF(ISERROR(B49),"ERORROR","OK") -> OK | M49: =IF(ISNA(C50),"NULL","NOT NULL") -> NOT NULL | N49: =COUNTIF(A:A,A49) -> 1 | O49: =IF(ISNA(VLOOKUP(J49,Vendors!A:A,1,FALSE)),"MISSING VENDER","VALID") -> MISSING VENDER | P49: =IF(ISNA(VLOOKUP(H49,'Customers'!A:A,1,FALSE)),"missing customer ","valid") -> valid | Q49: =IF(ISBLANK(D49),"INVALID","VALID") -> VALID | R49: =IF(ISNA(F49),"INVALID","VALID") -> VALID
A50: TRX100048 | B50: 45265 | C50: -28844.76 | D50: Expense | E50: Supplies | F50: Online | G50: West | I50: =_xlfn.XLOOKUP(H50,'Customers'!A50:A449,'Customers'!B50:B449," ") | J50: VEND1060 | K50: Where keep leader computer father brother a give. | L50: =IF(ISERROR(B50),"ERORROR","OK") -> OK | M50: =IF(ISNA(C51),"NULL","NOT NULL") -> NOT NULL | N50: =COUNTIF(A:A,A50) -> 1 | O50: =IF(ISNA(VLOOKUP(J50,Vendors!A:A,1,FALSE)),"MISSING VENDER","VALID") -> VALID | P50: =IF(ISNA(VLOOKUP(H50,'Customers'!A:A,1,FALSE)),"missing customer ","valid") -> missing customer | Q50: =IF(ISBLANK(D50),"INVALID","VALID") -> VALID | R50: =IF(ISNA(F50),"INVALID","VALID") -> VALID
A51: TRX100049 | B51: 44782 | C51: -66244 | D51: Expense | E51: Supplies | F51: Enterprise | G51: North | I51: =_xlfn.XLOOKUP(H51,'Customers'!A51:A450,'Customers'!B51:B450," ") | J51: VEND1089 | K51: Big itself serious. | L51: =IF(ISERROR(B51),"ERORROR","OK") -> OK | M51: =IF(ISNA(C52),"NULL","NOT NULL") -> NOT NULL | N51: =COUNTIF(A:A,A51) -> 1 | O51: =IF(ISNA(VLOOKUP(J51,Vendors!A:A,1,FALSE)),"MISSING VENDER","VALID") -> VALID | P51: =IF(ISNA(VLOOKUP(H51,'Customers'!A:A,1,FALSE)),"missing customer ","valid") -> missing customer | Q51: =IF(ISBLANK(D51),"INVALID","VALID") -> VALID | R51: =IF(ISNA(F51),"INVALID","VALID") -> VALID
A52: TRX100050 | B52: 45018 | C52: 15704.88 | D52: Asset | E52: Asset | F52: Enterprise | G52: East | I52: =_xlfn.XLOOKUP(H52,'Customers'!A52:A451,'Customers'!B52:B451," ") | K52: Test fill perform voice. | L52: =IF(ISERROR(B52),"ERORROR","OK") -> OK | M52: =IF(ISNA(C53),"NULL","NOT NULL") -> NOT NULL | N52: =COUNTIF(A:A,A52) -> 1 | O52: =IF(ISNA(VLOOKUP(J52,Vendors!A:A,1,FALSE)),"MISSING VENDER","VALID") -> MISSING VENDER | P52: =IF(ISNA(VLOOKUP(H52,'Customers'!A:A,1,FALSE)),"missing customer ","valid") -> missing customer | Q52: =IF(ISBLANK(D52),"INVALID","VALID") -> VALID | R52: =IF(ISNA(F52),"INVALID","VALID") -> VALID
A53: TRX100051 | B53: 44822 | C53: 209846.71 | D53: Revenue | E53: Subscription | F53: Retail | G53: South | H53: CUST10190 | I53: =_xlfn.XLOOKUP(H53,'Customers'!A53:A452,'Customers'!B53:B452," ") -> Sandoval-Morgan | K53: School common voice itself. | L53: =IF(ISERROR(B53),"ERORROR","OK") -> OK | M53: =IF(ISNA(C54),"NULL","NOT NULL") -> NOT NULL | N53: =COUNTIF(A:A,A53) -> 1 | O53: =IF(ISNA(VLOOKUP(J53,Vendors!A:A,1,FALSE)),"MISSING VENDER","VALID") -> MISSING VENDER | P53: =IF(ISNA(VLOOKUP(H53,'Customers'!A:A,1,FALSE)),"missing customer ","valid") -> valid | Q53: =IF(ISBLANK(D53),"INVALID","VALID") -> VALID | R53: =IF(ISNA(F53),"INVALID","VALID") -> VALID
A54: TRX100052 | B54: 44728 | C54: -45798.81 | D54: Expense | E54: Marketing | F54: Enterprise | G54: East | I54: =_xlfn.XLOOKUP(H54,'Customers'!A54:A453,'Customers'!B54:B453," ") | J54: VEND1011 | K54: Majority early special record sit scene price. | L54: =IF(ISERROR(B54),"ERORROR","OK") -> OK | M54: =IF(ISNA(C55),"NULL","NOT NULL") -> NOT NULL | N54: =COUNTIF(A:A,A54) -> 1 | O54: =IF(ISNA(VLOOKUP(J54,Vendors!A:A,1,FALSE)),"MISSING VENDER","VALID") -> VALID | P54: =IF(ISNA(VLOOKUP(H54,'Customers'!A:A,1,FALSE)),"missing customer ","valid") -> missing customer | Q54: =IF(ISBLANK(D54),"INVALID","VALID") -> VALID | R54: =IF(ISNA(F54),"INVALID","VALID") -> VALID
A55: TRX100053 | B55: 44687 | C55: -22712.23 | D55: Expense | E55: Payroll | F55: Enterprise | G55: North | I55: =_xlfn.XLOOKUP(H55,'Customers'!A55:A454,'Customers'!B55:B454," ") | J55: VEND1079 | K55: Daughter training suffer miss money. | L55: =IF(ISERROR(B55),"ERORROR","OK") -> OK | M55: =IF(ISNA(C56),"NULL","NOT NULL") -> NOT NULL | N55: =COUNTIF(A:A,A55) -> 1 | O55: =IF(ISNA(VLOOKUP(J55,Vendors!A:A,1,FALSE)),"MISSING VENDER","VALID") -> VALID | P55: =IF(ISNA(VLOOKUP(H55,'Customers'!A:A,1,FALSE)),"missing customer ","valid") -> missing customer | Q55: =IF(ISBLANK(D55),"INVALID","VALID") -> VALID | R55: =IF(ISNA(F55),"INVALID","VALID") -> VALID
A56: TRX100054 | B56: 44881 | C56: -51925.51 | D56: Expense | E56: Other | F56: Online | G56: East | I56: =_xlfn.XLOOKUP(H56,'Customers'!A56:A455,'Customers'!B56:B455," ") | J56: VEND1098 | K56: Including measure leave road leg mention. | L56: =IF(ISERROR(B56),"ERORROR","OK") -> OK | M56: =IF(ISNA(C57),"NULL","NOT NULL") -> NOT NULL | N56: =COUNTIF(A:A,A56) -> 1 | O56: =IF(ISNA(VLOOKUP(J56,Vendors!A:A,1,FALSE)),"MISSING VENDER","VALID") -> VALID | P56: =IF(ISNA(VLOOKUP(H56,'Customers'!A:A,1,FALSE)),"missing customer ","valid") -> missing customer | Q56: =IF(ISBLANK(D56),"INVALID","VALID") -> VALID | R56: =IF(ISNA(F56),"INVALID","VALID") -> VALID
A57: TRX100055 | B57: 44960 | C57: -42768.16 | D57: Expense | E57: Rent | F57: Online | G57: North | I57: =_xlfn.XLOOKUP(H57,'Customers'!A57:A456,'Customers'!B57:B456," ") | J57: VEND1082 | K57: Technology far reach thought probably cover increase. | L57: =IF(ISERROR(B57),"ERORROR","OK") -> OK | M57: =IF(ISNA(C58),"NULL","NOT NULL") -> NOT NULL | N57: =COUNTIF(A:A,A57) -> 1 | O57: =IF(ISNA(VLOOKUP(J57,Vendors!A:A,1,FALSE)),"MISSING VENDER","VALID") -> VALID | P57: =IF(ISNA(VLOOKUP(H57,'Customers'!A:A,1,FALSE)),"missing customer ","valid") -> missing customer | Q57: =IF(ISBLANK(D57),"INVALID","VALID") -> VALID | R57: =IF(ISNA(F57),"INVALID","VALID") -> VALID
A58: TRX100056 | B58: 44655 | C58: -22339.95 | D58: Expense | E58: Marketing | F58: Retail | G58: East | I58: =_xlfn.XLOOKUP(H58,'Customers'!A58:A457,'Customers'!B58:B457," ") | J58: VEND1001 | K58: Play prepare red goal. | L58: =IF(ISERROR(B58),"ERORROR","OK") -> OK | M58: =IF(ISNA(C59),"NULL","NOT NULL") -> NOT NULL | N58: =COUNTIF(A:A,A58) -> 1 | O58: =IF(ISNA(VLOOKUP(J58,Vendors!A:A,1,FALSE)),"MISSING VENDER","VALID") -> VALID | P58: =IF(ISNA(VLOOKUP(H58,'Customers'!A:A,1,FALSE)),"missing customer ","valid") -> missing customer | Q58: =IF(ISBLANK(D58),"INVALID","VALID") -> VALID | R58: =IF(ISNA(F58),"INVALID","VALID") -> VALID
A59: TRX100057 | B59: 44995 | C59: -43856.82 | D59: Expense | E59: Utilities | F59: Enterprise | G59: West | I59: =_xlfn.XLOOKUP(H59,'Customers'!A59:A458,'Customers'!B59:B458," ") | J59: VEND1042 | K59: Hard this despite certain they both provide machine. | L59: =IF(ISERROR(B59),"ERORROR","OK") -> OK | M59: =IF(ISNA(C60),"NULL","NOT NULL") -> NOT NULL | N59: =COUNTIF(A:A,A59) -> 1 | O59: =IF(ISNA(VLOOKUP(J59,Vendors!A:A,1,FALSE)),"MISSING VENDER","VALID") -> VALID | P59: =IF(ISNA(VLOOKUP(H59,'Customers'!A:A,1,FALSE)),"missing customer ","valid") -> missing customer | Q59: =IF(ISBLANK(D59),"INVALID","VALID") -> VALID | R59: =IF(ISNA(F59),"INVALID","VALID") -> VALID
A60: TRX100058 | B60: 44730 | C60: 86224.06 | D60: Revenue | E60: Product | F60: Retail | G60: East | H60: CUST10151 | I60: =_xlfn.XLOOKUP(H60,'Customers'!A60:A459,'Customers'!B60:B459," ") -> Horn, Henry and Walter | K60: Summer everyone his magazine six value week. | L60: =IF(ISERROR(B60),"ERORROR","OK") -> OK | M60: =IF(ISNA(C61),"NULL","NOT NULL") -> NOT NULL | N60: =COUNTIF(A:A,A60) -> 1 | O60: =IF(ISNA(VLOOKUP(J60,Vendors!A:A,1,FALSE)),"MISSING VENDER","VALID") -> MISSING VENDER | P60: =IF(ISNA(VLOOKUP(H60,'Customers'!A:A,1,FALSE)),"missing customer ","valid") -> valid | Q60: =IF(ISBLANK(D60),"INVALID","VALID") -> VALID | R60: =IF(ISNA(F60),"INVALID","VALID") -> VALID
A61: TRX100059 | B61: 44818 | C61: 196305.77 | D61: Revenue | E61: Service | F61: Enterprise | G61: West | H61: CUST10016 | I61: =_xlfn.XLOOKUP(H61,'Customers'!A61:A460,'Customers'!B61:B460," ") | K61: Pm like matter price personal for. | L61: =IF(ISERROR(B61),"ERORROR","OK") -> OK | M61: =IF(ISNA(C62),"NULL","NOT NULL") -> NOT NULL | N61: =COUNTIF(A:A,A61) -> 1 | O61: =IF(ISNA(VLOOKUP(J61,Vendors!A:A,1,FALSE)),"MISSING VENDER","VALID") -> MISSING VENDER | P61: =IF(ISNA(VLOOKUP(H61,'Customers'!A:A,1,FALSE)),"missing customer ","valid") -> valid | Q61: =IF(ISBLANK(D61),"INVALID","VALID") -> VALID | R61: =IF(ISNA(F61),"INVALID","VALID") -> VALID
A62: TRX100060 | B62: 45271 | C62: 144148.9 | D62: Revenue | E62: Product | F62: Online | G62: South | H62: CUST10049 | I62: =_xlfn.XLOOKUP(H62,'Customers'!A62:A461,'Customers'!B62:B461," ") | K62: True shoulder away. | L62: =IF(ISERROR(B62),"ERORROR","OK") -> OK | M62: =IF(ISNA(C63),"NULL","NOT NULL") -> NOT NULL | N62: =COUNTIF(A:A,A62) -> 1 | O62: =IF(ISNA(VLOOKUP(J62,Vendors!A:A,1,FALSE)),"MISSING VENDER","VALID") -> MISSING VENDER | P62: =IF(ISNA(VLOOKUP(H62,'Customers'!A:A,1,FALSE)),"missing customer ","valid") -> valid | Q62: =IF(ISBLANK(D62),"INVALID","VALID") -> VALID | R62: =IF(ISNA(F62),"INVALID","VALID") -> VALID
A63: TRX100061 | B63: 44872 | C63: 161193.89 | D63: Revenue | E63: Product | F63: Online | G63: South | H63: CUST10129 | I63: =_xlfn.XLOOKUP(H63,'Customers'!A63:A462,'Customers'!B63:B462," ") -> Rosales-Ochoa | K63: Page truth although under for water analysis. | L63: =IF(ISERROR(B63),"ERORROR","OK") -> OK | M63: =IF(ISNA(C64),"NULL","NOT NULL") -> NOT NULL | N63: =COUNTIF(A:A,A63) -> 1 | O63: =IF(ISNA(VLOOKUP(J63,Vendors!A:A,1,FALSE)),"MISSING VENDER","VALID") -> MISSING VENDER | P63: =IF(ISNA(VLOOKUP(H63,'Customers'!A:A,1,FALSE)),"missing customer ","valid") -> valid | Q63: =IF(ISBLANK(D63),"INVALID","VALID") -> VALID | R63: =IF(ISNA(F63),"INVALID","VALID") -> VALID
A64: TRX100062 | B64: 44808 | C64: 157413.67 | D64: Revenue | E64: Service | F64: Online | G64: West | H64: CUST10183 | I64: =_xlfn.XLOOKUP(H64,'Customers'!A64:A463,'Customers'!B64:B463," ") -> Maldonado Ltd | K64: Early choice speech follow fund measure. | L64: =IF(ISERROR(B64),"ERORROR","OK") -> OK | M64: =IF(ISNA(C65),"NULL","NOT NULL") -> NOT NULL | N64: =COUNTIF(A:A,A64) -> 1 | O64: =IF(ISNA(VLOOKUP(J64,Vendors!A:A,1,FALSE)),"MISSING VENDER","VALID") -> MISSING VENDER | P64: =IF(ISNA(VLOOKUP(H64,'Customers'!A:A,1,FALSE)),"missing customer ","valid") -> valid | Q64: =IF(ISBLANK(D64),"INVALID","VALID") -> VALID | R64: =IF(ISNA(F64),"INVALID","VALID") -> VALID
A65: TRX100063 | B65: 44583 | C65: 113690.25 | D65: Revenue | E65: Subscription | F65: Enterprise | G65: West | H65: CUST10348 | I65: =_xlfn.XLOOKUP(H65,'Customers'!A65:A464,'Customers'!B65:B464," ") -> Holmes, Brown and Burns | K65: Same whether interesting half Republican. | L65: =IF(ISERROR(B65),"ERORROR","OK") -> OK | M65: =IF(ISNA(C66),"NULL","NOT NULL") -> NOT NULL | N65: =COUNTIF(A:A,A65) -> 1 | O65: =IF(ISNA(VLOOKUP(J65,Vendors!A:A,1,FALSE)),"MISSING VENDER","VALID") -> MISSING VENDER | P65: =IF(ISNA(VLOOKUP(H65,'Customers'!A:A,1,FALSE)),"missing customer ","valid") -> valid | Q65: =IF(ISBLANK(D65),"INVALID","VALID") -> VALID | R65: =IF(ISNA(F65),"INVALID","VALID") -> VALID
A66: TRX100064 | B66: 45152 | C66: 194267.47 | D66: Revenue | E66: Subscription | F66: Online | G66: East | H66: CUST10075 | I66: =_xlfn.XLOOKUP(H66,'Customers'!A66:A465,'Customers'!B66:B465," ") -> Sanders Inc | K66: Half toward his. | L66: =IF(ISERROR(B66),"ERORROR","OK") -> OK | M66: =IF(ISNA(C67),"NULL","NOT NULL") -> NOT NULL | N66: =COUNTIF(A:A,A66) -> 1 | O66: =IF(ISNA(VLOOKUP(J66,Vendors!A:A,1,FALSE)),"MISSING VENDER","VALID") -> MISSING VENDER | P66: =IF(ISNA(VLOOKUP(H66,'Customers'!A:A,1,FALSE)),"missing customer ","valid") -> valid | Q66: =IF(ISBLANK(D66),"INVALID","VALID") -> VALID | R66: =IF(ISNA(F66),"INVALID","VALID") -> VALID
A67: TRX100065 | B67: 45018 | C67: -53590.9 | D67: Expense | E67: Marketing | F67: Enterprise | G67: South | I67: =_xlfn.XLOOKUP(H67,'Customers'!A67:A466,'Customers'!B67:B466," ") | J67: VEND1107 | K67: Source learn expect show. | L67: =IF(ISERROR(B67),"ERORROR","OK") -> OK | M67: =IF(ISNA(C68),"NULL","NOT NULL") -> NOT NULL | N67: =COUNTIF(A:A,A67) -> 1 | O67: =IF(ISNA(VLOOKUP(J67,Vendors!A:A,1,FALSE)),"MISSING VENDER","VALID") -> VALID | P67: =IF(ISNA(VLOOKUP(H67,'Customers'!A:A,1,FALSE)),"missing customer ","valid") -> missing customer | Q67: =IF(ISBLANK(D67),"INVALID","VALID") -> VALID | R67: =IF(ISNA(F67),"INVALID","VALID") -> VALID
A68: TRX100066 | B68: 44844 | C68: -29061.06 | D68: Expense | E68: Other | F68: Retail | G68: North | I68: =_xlfn.XLOOKUP(H68,'Customers'!A68:A467,'Customers'!B68:B467," ") | J68: VEND1019 | K68: House performance sign deep. | L68: =IF(ISERROR(B68),"ERORROR","OK") -> OK | M68: =IF(ISNA(C69),"NULL","NOT NULL") -> NOT NULL | N68: =COUNTIF(A:A,A68) -> 1 | O68: =IF(ISNA(VLOOKUP(J68,Vendors!A:A,1,FALSE)),"MISSING VENDER","VALID") -> VALID | P68: =IF(ISNA(VLOOKUP(H68,'Customers'!A:A,1,FALSE)),"missing customer ","valid") -> missing customer | Q68: =IF(ISBLANK(D68),"INVALID","VALID") -> VALID | R68: =IF(ISNA(F68),"INVALID","VALID") -> VALID
A69: TRX100067 | B69: 44904 | C69: -48080.35 | D69: Expense | E69: Rent | F69: Retail | G69: North | I69: =_xlfn.XLOOKUP(H69,'Customers'!A69:A468,'Customers'!B69:B468," ") | J69: VEND1030 | K69: Home now local perform by. | L69: =IF(ISERROR(B69),"ERORROR","OK") -> OK | M69: =IF(ISNA(C70),"NULL","NOT NULL") -> NOT NULL | N69: =COUNTIF(A:A,A69) -> 1 | O69: =IF(ISNA(VLOOKUP(J69,Vendors!A:A,1,FALSE)),"MISSING VENDER","VALID") -> VALID | P69: =IF(ISNA(VLOOKUP(H69,'Customers'!A:A,1,FALSE)),"missing customer ","valid") -> missing customer | Q69: =IF(ISBLANK(D69),"INVALID","VALID") -> VALID | R69: =IF(ISNA(F69),"INVALID","VALID") -> VALID
A70: TRX100068 | B70: 44749 | C70: 218024.69 | D70: Revenue | E70: Product | F70: Online | G70: North | H70: CUST10321 | I70: =_xlfn.XLOOKUP(H70,'Customers'!A70:A469,'Customers'!B70:B469," ") -> Whitney Inc | K70: Dog eight perhaps audience past eye. | L70: =IF(ISERROR(B70),"ERORROR","OK") -> OK | M70: =IF(ISNA(C71),"NULL","NOT NULL") -> NOT NULL | N70: =COUNTIF(A:A,A70) -> 1 | O70: =IF(ISNA(VLOOKUP(J70,Vendors!A:A,1,FALSE)),"MISSING VENDER","VALID") -> MISSING VENDER | P70: =IF(ISNA(VLOOKUP(H70,'Customers'!A:A,1,FALSE)),"missing customer ","valid") -> valid | Q70: =IF(ISBLANK(D70),"INVALID","VALID") -> VALID | R70: =IF(ISNA(F70),"INVALID","VALID") -> VALID
A71: TRX100069 | B71: 44749 | C71: -38127.82 | D71: Expense | E71: Rent | F71: Enterprise | G71: West | I71: =_xlfn.XLOOKUP(H71,'Customers'!A71:A470,'Customers'!B71:B470," ") | J71: VEND1086 | K71: His another government threat choose water fear. | L71: =IF(ISERROR(B71),"ERORROR","OK") -> OK | M71: =IF(ISNA(C72),"NULL","NOT NULL") -> NOT NULL | N71: =COUNTIF(A:A,A71) -> 1 | O71: =IF(ISNA(VLOOKUP(J71,Vendors!A:A,1,FALSE)),"MISSING VENDER","VALID") -> VALID | P71: =IF(ISNA(VLOOKUP(H71,'Customers'!A:A,1,FALSE)),"missing customer ","valid") -> missing customer | Q71: =IF(ISBLANK(D71),"INVALID","VALID") -> VALID | R71: =IF(ISNA(F71),"INVALID","VALID") -> VALID
A72: TRX100070 | B72: 44989 | C72: -31873.97 | D72: Expense | E72: Rent | F72: Retail | G72: North | I72: =_xlfn.XLOOKUP(H72,'Customers'!A72:A471,'Customers'!B72:B471," ") | J72: VEND1086 | K72: Enjoy keep pass write state even bank. | L72: =IF(ISERROR(B72),"ERORROR","OK") -> OK | M72: =IF(ISNA(C73),"NULL","NOT NULL") -> NOT NULL | N72: =COUNTIF(A:A,A72) -> 1 | O72: =IF(ISNA(VLOOKUP(J72,Vendors!A:A,1,FALSE)),"MISSING VENDER","VALID") -> VALID | P72: =IF(ISNA(VLOOKUP(H72,'Customers'!A:A,1,FALSE)),"missing customer ","valid") -> missing customer | Q72: =IF(ISBLANK(D72),"INVALID","VALID") -> VALID | R72: =IF(ISNA(F72),"INVALID","VALID") -> VALID
A73: TRX100071 | B73: 45082 | C73: 203084.24 | D73: Revenue | E73: Subscription | F73: Online | G73: West | H73: CUST10116 | I73: =_xlfn.XLOOKUP(H73,'Customers'!A73:A472,'Customers'!B73:B472," ") -> Archer PLC | K73: Possible talk model why we town decade. | L73: =IF(ISERROR(B73),"ERORROR","OK") -> OK | M73: =IF(ISNA(C74),"NULL","NOT NULL") -> NOT NULL | N73: =COUNTIF(A:A,A73) -> 1 | O73: =IF(ISNA(VLOOKUP(J73,Vendors!A:A,1,FALSE)),"MISSING VENDER","VALID") -> MISSING VENDER | P73: =IF(ISNA(VLOOKUP(H73,'Customers'!A:A,1,FALSE)),"missing customer ","valid") -> valid | Q73: =IF(ISBLANK(D73),"INVALID","VALID") -> VALID | R73: =IF(ISNA(F73),"INVALID","VALID") -> VALID
A74: TRX100072 | B74: 45290 | C74: 222948.96 | D74: Revenue | E74: Subscription | F74: Online | G74: North | H74: CUST10063 | I74: =_xlfn.XLOOKUP(H74,'Customers'!A74:A473,'Customers'!B74:B473," ") | K74: Black sit anyone language song show watch better. | L74: =IF(ISERROR(B74),"ERORROR","OK") -> OK | M74: =IF(ISNA(C75),"NULL","NOT NULL") -> NOT NULL | N74: =COUNTIF(A:A,A74) -> 1 | O74: =IF(ISNA(VLOOKUP(J74,Vendors!A:A,1,FALSE)),"MISSING VENDER","VALID") -> MISSING VENDER | P74: =IF(ISNA(VLOOKUP(H74,'Customers'!A:A,1,FALSE)),"missing customer ","valid") -> valid | Q74: =IF(ISBLANK(D74),"INVALID","VALID") -> VALID | R74: =IF(ISNA(F74),"INVALID","VALID") -> VALID
A75: TRX100073 | B75: 45270 | C75: 238667.54 | D75: Revenue | E75: Product | F75: Enterprise | G75: South | H75: CUST10137 | I75: =_xlfn.XLOOKUP(H75,'Customers'!A75:A474,'Customers'!B75:B474," ") -> Brown Group | K75: Rate reflect building guess well TV. | L75: =IF(ISERROR(B75),"ERORROR","OK") -> OK | M75: =IF(ISNA(C76),"NULL","NOT NULL") -> NOT NULL | N75: =COUNTIF(A:A,A75) -> 1 | O75: =IF(ISNA(VLOOKUP(J75,Vendors!A:A,1,FALSE)),"MISSING VENDER","VALID") -> MISSING VENDER | P75: =IF(ISNA(VLOOKUP(H75,'Customers'!A:A,1,FALSE)),"missing customer ","valid") -> valid | Q75: =IF(ISBLANK(D75),"INVALID","VALID") -> VALID | R75: =IF(ISNA(F75),"INVALID","VALID") -> VALID
A76: TRX100074 | B76: 44673 | C76: 132774.78 | D76: Revenue | E76: Subscription | F76: Retail | G76: South | H76: CUST10298 | I76: =_xlfn.XLOOKUP(H76,'Customers'!A76:A475,'Customers'!B76:B475," ") -> Acosta LLC | K76: And stop raise somebody nice. | L76: =IF(ISERROR(B76),"ERORROR","OK") -> OK | M76: =IF(ISNA(C77),"NULL","NOT NULL") -> NOT NULL | N76: =COUNTIF(A:A,A76) -> 1 | O76: =IF(ISNA(VLOOKUP(J76,Vendors!A:A,1,FALSE)),"MISSING VENDER","VALID") -> MISSING VENDER | P76: =IF(ISNA(VLOOKUP(H76,'Customers'!A:A,1,FALSE)),"missing customer ","valid") -> valid | Q76: =IF(ISBLANK(D76),"INVALID","VALID") -> VALID | R76: =IF(ISNA(F76),"INVALID","VALID") -> VALID
A77: TRX100075 | B77: 45186 | C77: 188545.69 | D77: Revenue | E77: Subscription | F77: Enterprise | G77: North | H77: CUST10187 | I77: =_xlfn.XLOOKUP(H77,'Customers'!A77:A476,'Customers'!B77:B476," ") -> Booker, Gomez and Jones | K77: Wonder increase hundred today final debate. | L77: =IF(ISERROR(B77),"ERORROR","OK") -> OK | M77: =IF(ISNA(C78),"NULL","NOT NULL") -> NOT NULL | N77: =COUNTIF(A:A,A77) -> 1 | O77: =IF(ISNA(VLOOKUP(J77,Vendors!A:A,1,FALSE)),"MISSING VENDER","VALID") -> MISSING VENDER | P77: =IF(ISNA(VLOOKUP(H77,'Customers'!A:A,1,FALSE)),"missing customer ","valid") -> valid | Q77: =IF(ISBLANK(D77),"INVALID","VALID") -> VALID | R77: =IF(ISNA(F77),"INVALID","VALID") -> VALID
A78: TRX100076 | B78: 45056 | C78: 138240.93 | D78: Revenue | E78: Service | F78: Retail | G78: East | H78: CUST10285 | I78: =_xlfn.XLOOKUP(H78,'Customers'!A78:A477,'Customers'!B78:B477," ") -> Fox-Garcia | K78: Pick fast one entire. | L78: =IF(ISERROR(B78),"ERORROR","OK") -> OK | M78: =IF(ISNA(C79),"NULL","NOT NULL") -> NOT NULL | N78: =COUNTIF(A:A,A78) -> 1 | O78: =IF(ISNA(VLOOKUP(J78,Vendors!A:A,1,FALSE)),"MISSING VENDER","VALID") -> MISSING VENDER | P78: =IF(ISNA(VLOOKUP(H78,'Customers'!A:A,1,FALSE)),"missing customer ","valid") -> valid | Q78: =IF(ISBLANK(D78),"INVALID","VALID") -> VALID | R78: =IF(ISNA(F78),"INVALID","VALID") -> VALID
A79: TRX100077 | B79: 45149 | C79: -14341.81 | D79: Expense | E79: Payroll | F79: Online | G79: North | I79: =_xlfn.XLOOKUP(H79,'Customers'!A79:A478,'Customers'!B79:B478," ") | J79: VEND1095 | K79: East very manager set act perhaps company ability. | L79: =IF(ISERROR(B79),"ERORROR","OK") -> OK | M79: =IF(ISNA(C80),"NULL","NOT NULL") -> NOT NULL | N79: =COUNTIF(A:A,A79) -> 1 | O79: =IF(ISNA(VLOOKUP(J79,Vendors!A:A,1,FALSE)),"MISSING VENDER","VALID") -> VALID | P79: =IF(ISNA(VLOOKUP(H79,'Customers'!A:A,1,FALSE)),"missing customer ","valid") -> missing customer | Q79: =IF(ISBLANK(D79),"INVALID","VALID") -> VALID | R79: =IF(ISNA(F79),"INVALID","VALID") -> VALID
A80: TRX100078 | B80: 44904 | C80: 163678.6 | D80: Revenue | E80: Product | F80: Enterprise | G80: West | H80: CUST10207 | I80: =_xlfn.XLOOKUP(H80,'Customers'!A80:A479,'Customers'!B80:B479," ") -> Compton LLC | K80: Three specific late economic serious word. | L80: =IF(ISERROR(B80),"ERORROR","OK") -> OK | M80: =IF(ISNA(C81),"NULL","NOT NULL") -> NOT NULL | N80: =COUNTIF(A:A,A80) -> 1 | O80: =IF(ISNA(VLOOKUP(J80,Vendors!A:A,1,FALSE)),"MISSING VENDER","VALID") -> MISSING VENDER | P80: =IF(ISNA(VLOOKUP(H80,'Customers'!A:A,1,FALSE)),"missing customer ","valid") -> valid | Q80: =IF(ISBLANK(D80),"INVALID","VALID") -> VALID | R80: =IF(ISNA(F80),"INVALID","VALID") -> VALID
A81: TRX100079 | B81: 44851 | C81: 198317.9 | D81: Revenue | E81: Product | F81: Enterprise | G81: West | H81: CUST10207 | I81: =_xlfn.XLOOKUP(H81,'Customers'!A81:A480,'Customers'!B81:B480," ") -> Compton LLC | K81: Continue beyond suffer plant student. | L81: =IF(ISERROR(B81),"ERORROR","OK") -> OK | M81: =IF(ISNA(C82),"NULL","NOT NULL") -> NOT NULL | N81: =COUNTIF(A:A,A81) -> 1 | O81: =IF(ISNA(VLOOKUP(J81,Vendors!A:A,1,FALSE)),"MISSING VENDER","VALID") -> MISSING VENDER | P81: =IF(ISNA(VLOOKUP(H81,'Customers'!A:A,1,FALSE)),"missing customer ","valid") -> valid | Q81: =IF(ISBLANK(D81),"INVALID","VALID") -> VALID | R81: =IF(ISNA(F81),"INVALID","VALID") -> VALID
A82: TRX100080 | B82: 45153 | C82: 188616.88 | D82: Revenue | E82: Product | F82: Retail | G82: North | H82: CUST10108 | I82: =_xlfn.XLOOKUP(H82,'Customers'!A82:A481,'Customers'!B82:B481," ") -> Boyd, James and Parsons | K82: Doctor surface girl friend everybody thousand under. | L82: =IF(ISERROR(B82),"ERORROR","OK") -> OK | M82: =IF(ISNA(C83),"NULL","NOT NULL") -> NOT NULL | N82: =COUNTIF(A:A,A82) -> 1 | O82: =IF(ISNA(VLOOKUP(J82,Vendors!A:A,1,FALSE)),"MISSING VENDER","VALID") -> MISSING VENDER | P82: =IF(ISNA(VLOOKUP(H82,'Customers'!A:A,1,FALSE)),"missing customer ","valid") -> valid | Q82: =IF(ISBLANK(D82),"INVALID","VALID") -> VALID | R82: =IF(ISNA(F82),"INVALID","VALID") -> VALID
A83: TRX100081 | B83: 44738 | C83: -25218.03 | D83: Expense | E83: Marketing | F83: Online | G83: East | I83: =_xlfn.XLOOKUP(H83,'Customers'!A83:A482,'Customers'!B83:B482," ") | J83: VEND1089 | K83: Kid item feeling less player. | L83: =IF(ISERROR(B83),"ERORROR","OK") -> OK | M83: =IF(ISNA(C84),"NULL","NOT NULL") -> NOT NULL | N83: =COUNTIF(A:A,A83) -> 1 | O83: =IF(ISNA(VLOOKUP(J83,Vendors!A:A,1,FALSE)),"MISSING VENDER","VALID") -> VALID | P83: =IF(ISNA(VLOOKUP(H83,'Customers'!A:A,1,FALSE)),"missing customer ","valid") -> missing customer | Q83: =IF(ISBLANK(D83),"INVALID","VALID") -> VALID | R83: =IF(ISNA(F83),"INVALID","VALID") -> VALID
A84: TRX100082 | B84: 45196 | C84: -15892.26 | D84: Expense | E84: Supplies | F84: Enterprise | G84: South | I84: =_xlfn.XLOOKUP(H84,'Customers'!A84:A483,'Customers'!B84:B483," ") | J84: VEND1025 | K84: Increase mouth your indeed. | L84: =IF(ISERROR(B84),"ERORROR","OK") -> OK | M84: =IF(ISNA(C85),"NULL","NOT NULL") -> NOT NULL | N84: =COUNTIF(A:A,A84) -> 1 | O84: =IF(ISNA(VLOOKUP(J84,Vendors!A:A,1,FALSE)),"MISSING VENDER","VALID") -> VALID | P84: =IF(ISNA(VLOOKUP(H84,'Customers'!A:A,1,FALSE)),"missing customer ","valid") -> missing customer | Q84: =IF(ISBLANK(D84),"INVALID","VALID") -> VALID | R84: =IF(ISNA(F84),"INVALID","VALID") -> VALID
A85: TRX100083 | B85: 44807 | C85: 199974.44 | D85: Revenue | E85: Subscription | F85: Enterprise | G85: South | H85: CUST10092 | I85: =_xlfn.XLOOKUP(H85,'Customers'!A85:A484,'Customers'!B85:B484," ") -> Jackson, Park and Lane | K85: Letter along six agent staff industry who. | L85: =IF(ISERROR(B85),"ERORROR","OK") -> OK | M85: =IF(ISNA(C86),"NULL","NOT NULL") -> NOT NULL | N85: =COUNTIF(A:A,A85) -> 1 | O85: =IF(ISNA(VLOOKUP(J85,Vendors!A:A,1,FALSE)),"MISSING VENDER","VALID") -> MISSING VENDER | P85: =IF(ISNA(VLOOKUP(H85,'Customers'!A:A,1,FALSE)),"missing customer ","valid") -> valid | Q85: =IF(ISBLANK(D85),"INVALID","VALID") -> VALID | R85: =IF(ISNA(F85),"INVALID","VALID") -> VALID
A86: TRX100084 | B86: 44686 | C86: 128923.58 | D86: Revenue | E86: Service | F86: Enterprise | G86: North | H86: CUST10082 | I86: =_xlfn.XLOOKUP(H86,'Customers'!A86:A485,'Customers'!B86:B485," ") | K86: Cell prevent goal view water shake matter effect. | L86: =IF(ISERROR(B86),"ERORROR","OK") -> OK | M86: =IF(ISNA(C87),"NULL","NOT NULL") -> NOT NULL | N86: =COUNTIF(A:A,A86) -> 1 | O86: =IF(ISNA(VLOOKUP(J86,Vendors!A:A,1,FALSE)),"MISSING VENDER","VALID") -> MISSING VENDER | P86: =IF(ISNA(VLOOKUP(H86,'Customers'!A:A,1,FALSE)),"missing customer ","valid") -> valid | Q86: =IF(ISBLANK(D86),"INVALID","VALID") -> VALID | R86: =IF(ISNA(F86),"INVALID","VALID") -> VALID
A87: TRX100085 | B87: 44982 | C87: 67222.23 | D87: Revenue | E87: Service | F87: Online | G87: West | H87: CUST10209 | I87: =_xlfn.XLOOKUP(H87,'Customers'!A87:A486,'Customers'!B87:B486," ") -> Ward PLC | K87: End cover a enough speak figure. | L87: =IF(ISERROR(B87),"ERORROR","OK") -> OK | M87: =IF(ISNA(C88),"NULL","NOT NULL") -> NOT NULL | N87: =COUNTIF(A:A,A87) -> 1 | O87: =IF(ISNA(VLOOKUP(J87,Vendors!A:A,1,FALSE)),"MISSING VENDER","VALID") -> MISSING VENDER | P87: =IF(ISNA(VLOOKUP(H87,'Customers'!A:A,1,FALSE)),"missing customer ","valid") -> valid | Q87: =IF(ISBLANK(D87),"INVALID","VALID") -> VALID | R87: =IF(ISNA(F87),"INVALID","VALID") -> VALID
A88: TRX100086 | B88: 44923 | C88: 186952.56 | D88: Revenue | E88: Subscription | F88: Online | G88: West | H88: CUST10089 | I88: =_xlfn.XLOOKUP(H88,'Customers'!A88:A487,'Customers'!B88:B487," ") -> Martinez Inc | K88: Economic behind young American artist main personal. | L88: =IF(ISERROR(B88),"ERORROR","OK") -> OK | M88: =IF(ISNA(C89),"NULL","NOT NULL") -> NOT NULL | N88: =COUNTIF(A:A,A88) -> 1 | O88: =IF(ISNA(VLOOKUP(J88,Vendors!A:A,1,FALSE)),"MISSING VENDER","VALID") -> MISSING VENDER | P88: =IF(ISNA(VLOOKUP(H88,'Customers'!A:A,1,FALSE)),"missing customer ","valid") -> valid | Q88: =IF(ISBLANK(D88),"INVALID","VALID") -> VALID | R88: =IF(ISNA(F88),"INVALID","VALID") -> VALID
A89: TRX100087 | B89: 45116 | C89: 164462.06 | D89: Revenue | E89: Service | F89: Retail | G89: East | H89: CUST10042 | I89: =_xlfn.XLOOKUP(H89,'Customers'!A89:A488,'Customers'!B89:B488," ") | K89: Girl reveal order deep chair cut sit. | L89: =IF(ISERROR(B89),"ERORROR","OK") -> OK | M89: =IF(ISNA(C90),"NULL","NOT NULL") -> NOT NULL | N89: =COUNTIF(A:A,A89) -> 1 | O89: =IF(ISNA(VLOOKUP(J89,Vendors!A:A,1,FALSE)),"MISSING VENDER","VALID") -> MISSING VENDER | P89: =IF(ISNA(VLOOKUP(H89,'Customers'!A:A,1,FALSE)),"missing customer ","valid") -> valid | Q89: =IF(ISBLANK(D89),"INVALID","VALID") -> VALID | R89: =IF(ISNA(F89),"INVALID","VALID") -> VALID
A90: TRX100088 | B90: 44872 | C90: 18077.56 | D90: Equity | E90: Equity | F90: Enterprise | G90: South | I90: =_xlfn.XLOOKUP(H90,'Customers'!A90:A489,'Customers'!B90:B489," ") | K90: Once fact interest difference section remain. | L90: =IF(ISERROR(B90),"ERORROR","OK") -> OK | M90: =IF(ISNA(C91),"NULL","NOT NULL") -> NOT NULL | N90: =COUNTIF(A:A,A90) -> 1 | O90: =IF(ISNA(VLOOKUP(J90,Vendors!A:A,1,FALSE)),"MISSING VENDER","VALID") -> MISSING VENDER | P90: =IF(ISNA(VLOOKUP(H90,'Customers'!A:A,1,FALSE)),"missing customer ","valid") -> missing customer | Q90: =IF(ISBLANK(D90),"INVALID","VALID") -> VALID | R90: =IF(ISNA(F90),"INVALID","VALID") -> VALID
A91: TRX100089 | B91: 45213 | C91: 72337.28 | D91: Revenue | E91: Service | F91: Online | G91: South | H91: CUST10157 | I91: =_xlfn.XLOOKUP(H91,'Customers'!A91:A490,'Customers'!B91:B490," ") -> Anderson, Weeks and Gonzalez | K91: Able finish they defense yet activity. | L91: =IF(ISERROR(B91),"ERORROR","OK") -> OK | M91: =IF(ISNA(C92),"NULL","NOT NULL") -> NOT NULL | N91: =COUNTIF(A:A,A91) -> 1 | O91: =IF(ISNA(VLOOKUP(J91,Vendors!A:A,1,FALSE)),"MISSING VENDER","VALID") -> MISSING VENDER | P91: =IF(ISNA(VLOOKUP(H91,'Customers'!A:A,1,FALSE)),"missing customer ","valid") -> valid | Q91: =IF(ISBLANK(D91),"INVALID","VALID") -> VALID | R91: =IF(ISNA(F91),"INVALID","VALID") -> VALID
A92: TRX100090 | B92: 44760 | C92: -40667.5 | D92: Expense | E92: Rent | F92: Online | G92: South | I92: =_xlfn.XLOOKUP(H92,'Customers'!A92:A491,'Customers'!B92:B491," ") | J92: VEND1090 | K92: Instead age animal popular parent baby. | L92: =IF(ISERROR(B92),"ERORROR","OK") -> OK | M92: =IF(ISNA(C93),"NULL","NOT NULL") -> NOT NULL | N92: =COUNTIF(A:A,A92) -> 1 | O92: =IF(ISNA(VLOOKUP(J92,Vendors!A:A,1,FALSE)),"MISSING VENDER","VALID") -> VALID | P92: =IF(ISNA(VLOOKUP(H92,'Customers'!A:A,1,FALSE)),"missing customer ","valid") -> missing customer | Q92: =IF(ISBLANK(D92),"INVALID","VALID") -> VALID | R92: =IF(ISNA(F92),"INVALID","VALID") -> VALID
A93: TRX100091 | B93: 44565 | C93: 177006.22 | D93: Revenue | E93: Product | F93: Retail | G93: West | H93: CUST10212 | I93: =_xlfn.XLOOKUP(H93,'Customers'!A93:A492,'Customers'!B93:B492," ") -> Skinner LLC | K93: Choose per range week. | L93: =IF(ISERROR(B93),"ERORROR","OK") -> OK | M93: =IF(ISNA(C94),"NULL","NOT NULL") -> NOT NULL | N93: =COUNTIF(A:A,A93) -> 1 | O93: =IF(ISNA(VLOOKUP(J93,Vendors!A:A,1,FALSE)),"MISSING VENDER","VALID") -> MISSING VENDER | P93: =IF(ISNA(VLOOKUP(H93,'Customers'!A:A,1,FALSE)),"missing customer ","valid") -> valid | Q93: =IF(ISBLANK(D93),"INVALID","VALID") -> VALID | R93: =IF(ISNA(F93),"INVALID","VALID") -> VALID
A94: TRX100092 | B94: 44759 | C94: -33821.98 | D94: Expense | E94: Other | F94: Online | G94: West | I94: =_xlfn.XLOOKUP(H94,'Customers'!A94:A493,'Customers'!B94:B493," ") | J94: VEND1059 | K94: Lay buy bar century. | L94: =IF(ISERROR(B94),"ERORROR","OK") -> OK | M94: =IF(ISNA(C95),"NULL","NOT NULL") -> NOT NULL | N94: =COUNTIF(A:A,A94) -> 1 | O94: =IF(ISNA(VLOOKUP(J94,Vendors!A:A,1,FALSE)),"MISSING VENDER","VALID") -> VALID | P94: =IF(ISNA(VLOOKUP(H94,'Customers'!A:A,1,FALSE)),"missing customer ","valid") -> missing customer | Q94: =IF(ISBLANK(D94),"INVALID","VALID") -> VALID | R94: =IF(ISNA(F94),"INVALID","VALID") -> VALID
A95: TRX100093 | B95: 44749 | C95: 113760.1 | D95: Revenue | E95: Service | F95: Enterprise | G95: South | H95: CUST10232 | I95: =_xlfn.XLOOKUP(H95,'Customers'!A95:A494,'Customers'!B95:B494," ") -> Nichols-Franklin | K95: Congress whose main matter coach loss executive. | L95: =IF(ISERROR(B95),"ERORROR","OK") -> OK | M95: =IF(ISNA(C96),"NULL","NOT NULL") -> NOT NULL | N95: =COUNTIF(A:A,A95) -> 1 | O95: =IF(ISNA(VLOOKUP(J95,Vendors!A:A,1,FALSE)),"MISSING VENDER","VALID") -> MISSING VENDER | P95: =IF(ISNA(VLOOKUP(H95,'Customers'!A:A,1,FALSE)),"missing customer ","valid") -> valid | Q95: =IF(ISBLANK(D95),"INVALID","VALID") -> VALID | R95: =IF(ISNA(F95),"INVALID","VALID") -> VALID
A96: TRX100094 | B96: 44618 | C96: 68040.32 | D96: Revenue | E96: Service | F96: Retail | G96: South | H96: CUST10121 | I96: =_xlfn.XLOOKUP(H96,'Customers'!A96:A495,'Customers'!B96:B495," ") -> Evans-Green | K96: Bar rock democratic positive live easy grow. | L96: =IF(ISERROR(B96),"ERORROR","OK") -> OK | M96: =IF(ISNA(C97),"NULL","NOT NULL") -> NOT NULL | N96: =COUNTIF(A:A,A96) -> 1 | O96: =IF(ISNA(VLOOKUP(J96,Vendors!A:A,1,FALSE)),"MISSING VENDER","VALID") -> MISSING VENDER | P96: =IF(ISNA(VLOOKUP(H96,'Customers'!A:A,1,FALSE)),"missing customer ","valid") -> valid | Q96: =IF(ISBLANK(D96),"INVALID","VALID") -> VALID | R96: =IF(ISNA(F96),"INVALID","VALID") -> VALID
A97: TRX100095 | B97: 45132 | C97: 114168.76 | D97: Revenue | E97: Product | F97: Retail | G97: West | H97: CUST10237 | I97: =_xlfn.XLOOKUP(H97,'Customers'!A97:A496,'Customers'!B97:B496," ") -> Snow, Campbell and Dominguez | K97: Certainly believe white money. | L97: =IF(ISERROR(B97),"ERORROR","OK") -> OK | M97: =IF(ISNA(C98),"NULL","NOT NULL") -> NOT NULL | N97: =COUNTIF(A:A,A97) -> 1 | O97: =IF(ISNA(VLOOKUP(J97,Vendors!A:A,1,FALSE)),"MISSING VENDER","VALID") -> MISSING VENDER | P97: =IF(ISNA(VLOOKUP(H97,'Customers'!A:A,1,FALSE)),"missing customer ","valid") -> valid | Q97: =IF(ISBLANK(D97),"INVALID","VALID") -> VALID | R97: =IF(ISNA(F97),"INVALID","VALID") -> VALID
A98: TRX100096 | B98: 45034 | C98: 104796.05 | D98: Revenue | E98: Product | F98: Online | G98: West | H98: CUST10266 | I98: =_xlfn.XLOOKUP(H98,'Customers'!A98:A497,'Customers'!B98:B497," ") -> Leonard-Howard | K98: Support visit else lead call. | L98: =IF(ISERROR(B98),"ERORROR","OK") -> OK | M98: =IF(ISNA(C99),"NULL","NOT NULL") -> NOT NULL | N98: =COUNTIF(A:A,A98) -> 1 | O98: =IF(ISNA(VLOOKUP(J98,Vendors!A:A,1,FALSE)),"MISSING VENDER","VALID") -> MISSING VENDER | P98: =IF(ISNA(VLOOKUP(H98,'Customers'!A:A,1,FALSE)),"missing customer ","valid") -> valid | Q98: =IF(ISBLANK(D98),"INVALID","VALID") -> VALID | R98: =IF(ISNA(F98),"INVALID","VALID") -> VALID
A99: TRX100097 | B99: 44637 | C99: -40864.74 | D99: Expense | E99: Other | F99: Retail | G99: East | I99: =_xlfn.XLOOKUP(H99,'Customers'!A99:A498,'Customers'!B99:B498," ") | J99: VEND1072 | K99: But share truth conference seem TV. | L99: =IF(ISERROR(B99),"ERORROR","OK") -> OK | M99: =IF(ISNA(C100),"NULL","NOT NULL") -> NOT NULL | N99: =COUNTIF(A:A,A99) -> 1 | O99: =IF(ISNA(VLOOKUP(J99,Vendors!A:A,1,FALSE)),"MISSING VENDER","VALID") -> VALID | P99: =IF(ISNA(VLOOKUP(H99,'Customers'!A:A,1,FALSE)),"missing customer ","valid") -> missing customer | Q99: =IF(ISBLANK(D99),"INVALID","VALID") -> VALID | R99: =IF(ISNA(F99),"INVALID","VALID") -> VALID
A100: TRX100098 | B100: 45167 | C100: -10569.47 | D100: Expense | E100: Supplies | F100: Retail | G100: East | I100: =_xlfn.XLOOKUP(H100,'Customers'!A100:A499,'Customers'!B100:B499," ") | J100: VEND1065 | K100: Officer agree interesting nice risk from medical some. | L100: =IF(ISERROR(B100),"ERORROR","OK") -> OK | M100: =IF(ISNA(C101),"NULL","NOT NULL") -> NOT NULL | N100: =COUNTIF(A:A,A100) -> 1 | O100: =IF(ISNA(VLOOKUP(J100,Vendors!A:A,1,FALSE)),"MISSING VENDER","VALID") -> VALID | P100: =IF(ISNA(VLOOKUP(H100,'Customers'!A:A,1,FALSE)),"missing customer ","valid") -> missing customer | Q100: =IF(ISBLANK(D100),"INVALID","VALID") -> VALID | R100: =IF(ISNA(F100),"INVALID","VALID") -> VALID
...

Sheet Customers
A1: customer_id | B1: customer_name | C1: segment | D1: join_date | E1: region | F1: status | H1: PK uniqueness
A2: CUST10000 | B2: Johnson, Olson and Smith | C2: Online | D2: 43918 | E2: North | F2: Active | H2: =COUNTIF(A:A,A2) -> 1
A3: CUST10001 | B3: Colon-Valdez | C3: Enterprise | D3: 43146 | E3: West | F3: Active | H3: =COUNTIF(A:A,A3) -> 1
A4: CUST10002 | B4: Henry, Jones and Farley | C4: Online | D4: 44641 | E4: North | F4: Active | H4: =COUNTIF(A:A,A4) -> 1
A5: CUST10003 | B5: Williams-Dalton | C5: Retail | D5: 44277 | E5: West | F5: Active | H5: =COUNTIF(A:A,A5) -> 1
A6: CUST10004 | B6: Fisher-Serrano | C6: Enterprise | D6: 43406 | E6: East | F6: Active | H6: =COUNTIF(A:A,A6) -> 1
A7: CUST10005 | B7: Jennings Ltd | C7: Online | D7: 43663 | E7: South | F7: Active | H7: =COUNTIF(A:A,A7) -> 1
A8: CUST10006 | B8: Tate-Haas | C8: Retail | D8: 45212 | E8: West | F8: Active | H8: =COUNTIF(A:A,A8) -> 1
A9: CUST10007 | B9: Brooks, Aguilar and Young | C9: Enterprise | D9: 43234 | E9: North | F9: Active | H9: =COUNTIF(A:A,A9) -> 1
A10: CUST10008 | B10: Herrera-Ingram | C10: Retail | D10: 43350 | E10: East | F10: Active | H10: =COUNTIF(A:A,A10) -> 1
A11: CUST10009 | B11: Dunn, Graham and Brown | C11: Retail | D11: 44229 | E11: West | F11: Active | H11: =COUNTIF(A:A,A11) -> 1
A12: CUST10010 | B12: Moore, Walker and Gutierrez | C12: Retail | D12: 42831 | E12: East | F12: Active | H12: =COUNTIF(A:A,A12) -> 1
A13: CUST10011 | B13: Turner-Lawson | C13: Enterprise | D13: 42920 | E13: West | F13: Active | H13: =COUNTIF(A:A,A13) -> 1
... A401: CUST10399 | B401: Marshall-Horne | C401: Enterprise | D401: 43563 | E401: East | F401: Inactive | H401: =COUNTIF(A:A,A401) -> 1

Sheet Budget
A1: DATE | B1: business_unit | C1: budgeted_revenue | D1: budgeted_expense | E1: re-exp | F1: PK uniqueness
A2: 44562 | B2: Retail | C2: 1530660 | D2: 1259760 | E2: =Budget[[#This Row],[budgeted_revenue]] - Budget[[#This Row],[budgeted_expense]] -> 270900 | F2: =COUNTIF(A:A,A2) -> 3
A3: 44562 | B3: Enterprise | C3: 1689240 | D3: 1152615 | E3: =Budget[[#This Row],[budgeted_revenue]] - Budget[[#This Row],[budgeted_expense]] -> 536625 | F3: =COUNTIF(A:A,A3) -> 3
A4: 44562 | B4: Online | C4: 2069088 | D4: 1776169 | E4: =Budget[[#This Row],[budgeted_revenue]] - Budget[[#This Row],[budgeted_expense]] -> 292919 | F4: =COUNTIF(A:A,A4) -> 3
A5: 44593 | B5: Retail | C5: 1836984 | D5: 1201730 | E5: =Budget[[#This Row],[budgeted_revenue]] - Budget[[#This Row],[budgeted_expense]] -> 635254 | F5: =COUNTIF(A:A,A5) -> 3
A6: 44593 | B6: Enterprise | C6: 1923012 | D6: 1454263 | E6: =Budget[[#This Row],[budgeted_revenue]] - Budget[[#This Row],[budgeted_expense]] -> 468749 | F6: =COUNTIF(A:A,A6) -> 3
A7: 44593 | B7: Online | C7: 1516272 | D7: 1117069 | E7: =Budget[[#This Row],[budgeted_revenue]] - Budget[[#This Row],[budgeted_expense]] -> 399203 | F7: =COUNTIF(A:A,A7) -> 3
A8: 44621 | B8: Retail | C8: 1510920 | D8: 1106833 | E8: =Budget[[#This Row],[budgeted_revenue]] - Budget[[#This Row],[budgeted_expense]] -> 404087 | F8: =COUNTIF(A:A,A8) -> 3
A9: 44621 | B9: Enterprise | C9: 1576692 | D9: 959653 | E9: =Budget[[#This Row],[budgeted_revenue]] - Budget[[#This Row],[budgeted_expense]] -> 617039 | F9: =COUNTIF(A:A,A9) -> 3
A10: 44621 | B10: Online | C10: 2119464 | D10: 1677676 | E10: =Budget[[#This Row],[budgeted_revenue]] - Budget[[#This Row],[budgeted_expense]] -> 441788 | F10: =COUNTIF(A:A,A10) -> 3
A11: 44652 | B11: Retail | C11: 1731204 | D11: 1275919 | E11: =Budget[[#This Row],[budgeted_revenue]] - Budget[[#This Row],[budgeted_expense]] -> 455285 | F11: =COUNTIF(A:A,A11) -> 3
A12: 44652 | B12: Enterprise | C12: 2042184 | D12: 1592655 | E12: =Budget[[#This Row],[budgeted_revenue]] - Budget[[#This Row],[budgeted_expense]] -> 449529 | F12: =COUNTIF(A:A,A12) -> 3
A13: 44652 | B13: Online | C13: 2132844 | D13: 1388082 | E13: =Budget[[#This Row],[budgeted_revenue]] - Budget[[#This Row],[budgeted_expense]] -> 744762 | F13: =COUNTIF(A:A,A13) -> 3
... A73: 45261 | B73: Online | C73: 2263008 | D73: 1662605 | E73: =Budget[[#This Row],[budgeted_revenue]] - Budget[[#This Row],[budgeted_expense]] -> 600403 | F73: =COUNTIF(A:A,A73) -> 3
F74: =COUNTIF(A:A,A74) -> 0
